{
  "schemaVersion": 2,
  "id": "people-and-body/person-sport",
  "image": "people-and-body/person-sport.png",
  "setName": "Pixel Emoji Base Set",
  "group": "People & Body",
  "subGroup": "person-sport",
  "part": 1,
  "partCount": 1,
  "createdDate": "2026-07-23",
  "author": "Lewis Moten",
  "url": "https://lewismoten.com",
  "cellSize": 12,
  "cellPadding": 2,
  "slotSize": 16,
  "columns": 16,
  "rows": 3,
  "capacity": 48,
  "imageWidth": 272,
  "imageHeight": 112,
  "headerHeight": 40,
  "footerHeight": 24,
  "entries": [
    {
      "index": 0,
      "row": 0,
      "column": 0,
      "x": 10,
      "y": 42,
      "width": 12,
      "height": 12,
      "key": "personFencing",
      "name": "person fencing",
      "emoji": "🤺",
      "codePoints": ["1F93A"],
      "group": "People & Body",
      "subGroup": "person-sport",
      "order": 1903,
      "sequenceType": "single",
      "active": true
    },
    {
      "index": 1,
      "row": 0,
      "column": 1,
      "x": 26,
      "y": 42,
      "width": 12,
      "height": 12,
      "key": "horseRacing",
      "name": "horse racing",
      "emoji": "🏇",
      "codePoints": ["1F3C7"],
      "group": "People & Body",
      "subGroup": "person-sport",
      "order": 1904,
      "sequenceType": "single",
      "active": true
    },
    {
      "index": 2,
      "row": 0,
      "column": 2,
      "x": 42,
      "y": 42,
      "width": 12,
      "height": 12,
      "key": "skier",
      "name": "skier",
      "emoji": "⛷️",
      "codePoints": ["26F7", "FE0F"],
      "group": "People & Body",
      "subGroup": "person-sport",
      "order": 1910,
      "sequenceType": "single",
      "active": true
    },
    {
      "index": 3,
      "row": 0,
      "column": 3,
      "x": 58,
      "y": 42,
      "width": 12,
      "height": 12,
      "key": "snowboarder",
      "name": "snowboarder",
      "emoji": "🏂",
      "codePoints": ["1F3C2"],
      "group": "People & Body",
      "subGroup": "person-sport",
      "order": 1911,
      "sequenceType": "single",
      "active": true
    },
    {
      "index": 4,
      "row": 0,
      "column": 4,
      "x": 74,
      "y": 42,
      "width": 12,
      "height": 12,
      "key": "personGolfing",
      "name": "person golfing",
      "emoji": "🏌️",
      "codePoints": ["1F3CC", "FE0F"],
      "group": "People & Body",
      "subGroup": "person-sport",
      "order": 1917,
      "sequenceType": "single",
      "active": true
    },
    {
      "index": 5,
      "row": 0,
      "column": 5,
      "x": 90,
      "y": 42,
      "width": 12,
      "height": 12,
      "key": "manGolfing",
      "name": "man golfing",
      "emoji": "🏌️‍♂️",
      "codePoints": ["1F3CC", "FE0F", "200D", "2642", "FE0F"],
      "group": "People & Body",
      "subGroup": "person-sport",
      "order": 1923,
      "sequenceType": "zwj",
      "active": true
    },
    {
      "index": 6,
      "row": 0,
      "column": 6,
      "x": 106,
      "y": 42,
      "width": 12,
      "height": 12,
      "key": "womanGolfing",
      "name": "woman golfing",
      "emoji": "🏌️‍♀️",
      "codePoints": ["1F3CC", "FE0F", "200D", "2640", "FE0F"],
      "group": "People & Body",
      "subGroup": "person-sport",
      "order": 1929,
      "sequenceType": "zwj",
      "active": true
    },
    {
      "index": 7,
      "row": 0,
      "column": 7,
      "x": 122,
      "y": 42,
      "width": 12,
      "height": 12,
      "key": "personSurfing",
      "name": "person surfing",
      "emoji": "🏄",
      "codePoints": ["1F3C4"],
      "group": "People & Body",
      "subGroup": "person-sport",
      "order": 1935,
      "sequenceType": "single",
      "active": true
    },
    {
      "index": 8,
      "row": 0,
      "column": 8,
      "x": 138,
      "y": 42,
      "width": 12,
      "height": 12,
      "key": "manSurfing",
      "name": "man surfing",
      "emoji": "🏄‍♂️",
      "codePoints": ["1F3C4", "200D", "2642", "FE0F"],
      "group": "People & Body",
      "subGroup": "person-sport",
      "order": 1941,
      "sequenceType": "zwj",
      "active": true
    },
    {
      "index": 9,
      "row": 0,
      "column": 9,
      "x": 154,
      "y": 42,
      "width": 12,
      "height": 12,
      "key": "womanSurfing",
      "name": "woman surfing",
      "emoji": "🏄‍♀️",
      "codePoints": ["1F3C4", "200D", "2640", "FE0F"],
      "group": "People & Body",
      "subGroup": "person-sport",
      "order": 1947,
      "sequenceType": "zwj",
      "active": true
    },
    {
      "index": 10,
      "row": 0,
      "column": 10,
      "x": 170,
      "y": 42,
      "width": 12,
      "height": 12,
      "key": "personRowingBoat",
      "name": "person rowing boat",
      "emoji": "🚣",
      "codePoints": ["1F6A3"],
      "group": "People & Body",
      "subGroup": "person-sport",
      "order": 1953,
      "sequenceType": "single",
      "active": true
    },
    {
      "index": 11,
      "row": 0,
      "column": 11,
      "x": 186,
      "y": 42,
      "width": 12,
      "height": 12,
      "key": "manRowingBoat",
      "name": "man rowing boat",
      "emoji": "🚣‍♂️",
      "codePoints": ["1F6A3", "200D", "2642", "FE0F"],
      "group": "People & Body",
      "subGroup": "person-sport",
      "order": 1959,
      "sequenceType": "zwj",
      "active": true
    },
    {
      "index": 12,
      "row": 0,
      "column": 12,
      "x": 202,
      "y": 42,
      "width": 12,
      "height": 12,
      "key": "womanRowingBoat",
      "name": "woman rowing boat",
      "emoji": "🚣‍♀️",
      "codePoints": ["1F6A3", "200D", "2640", "FE0F"],
      "group": "People & Body",
      "subGroup": "person-sport",
      "order": 1965,
      "sequenceType": "zwj",
      "active": true
    },
    {
      "index": 13,
      "row": 0,
      "column": 13,
      "x": 218,
      "y": 42,
      "width": 12,
      "height": 12,
      "key": "personSwimming",
      "name": "person swimming",
      "emoji": "🏊",
      "codePoints": ["1F3CA"],
      "group": "People & Body",
      "subGroup": "person-sport",
      "order": 1971,
      "sequenceType": "single",
      "active": true
    },
    {
      "index": 14,
      "row": 0,
      "column": 14,
      "x": 234,
      "y": 42,
      "width": 12,
      "height": 12,
      "key": "manSwimming",
      "name": "man swimming",
      "emoji": "🏊‍♂️",
      "codePoints": ["1F3CA", "200D", "2642", "FE0F"],
      "group": "People & Body",
      "subGroup": "person-sport",
      "order": 1977,
      "sequenceType": "zwj",
      "active": true
    },
    {
      "index": 15,
      "row": 0,
      "column": 15,
      "x": 250,
      "y": 42,
      "width": 12,
      "height": 12,
      "key": "womanSwimming",
      "name": "woman swimming",
      "emoji": "🏊‍♀️",
      "codePoints": ["1F3CA", "200D", "2640", "FE0F"],
      "group": "People & Body",
      "subGroup": "person-sport",
      "order": 1983,
      "sequenceType": "zwj",
      "active": true
    },
    {
      "index": 16,
      "row": 1,
      "column": 0,
      "x": 10,
      "y": 58,
      "width": 12,
      "height": 12,
      "key": "personBouncingBall",
      "name": "person bouncing ball",
      "emoji": "⛹️",
      "codePoints": ["26F9", "FE0F"],
      "group": "People & Body",
      "subGroup": "person-sport",
      "order": 1989,
      "sequenceType": "single",
      "active": true
    },
    {
      "index": 17,
      "row": 1,
      "column": 1,
      "x": 26,
      "y": 58,
      "width": 12,
      "height": 12,
      "key": "manBouncingBall",
      "name": "man bouncing ball",
      "emoji": "⛹️‍♂️",
      "codePoints": ["26F9", "FE0F", "200D", "2642", "FE0F"],
      "group": "People & Body",
      "subGroup": "person-sport",
      "order": 1995,
      "sequenceType": "zwj",
      "active": true
    },
    {
      "index": 18,
      "row": 1,
      "column": 2,
      "x": 42,
      "y": 58,
      "width": 12,
      "height": 12,
      "key": "womanBouncingBall",
      "name": "woman bouncing ball",
      "emoji": "⛹️‍♀️",
      "codePoints": ["26F9", "FE0F", "200D", "2640", "FE0F"],
      "group": "People & Body",
      "subGroup": "person-sport",
      "order": 2001,
      "sequenceType": "zwj",
      "active": true
    },
    {
      "index": 19,
      "row": 1,
      "column": 3,
      "x": 58,
      "y": 58,
      "width": 12,
      "height": 12,
      "key": "personLiftingWeights",
      "name": "person lifting weights",
      "emoji": "🏋️",
      "codePoints": ["1F3CB", "FE0F"],
      "group": "People & Body",
      "subGroup": "person-sport",
      "order": 2007,
      "sequenceType": "single",
      "active": true
    },
    {
      "index": 20,
      "row": 1,
      "column": 4,
      "x": 74,
      "y": 58,
      "width": 12,
      "height": 12,
      "key": "manLiftingWeights",
      "name": "man lifting weights",
      "emoji": "🏋️‍♂️",
      "codePoints": ["1F3CB", "FE0F", "200D", "2642", "FE0F"],
      "group": "People & Body",
      "subGroup": "person-sport",
      "order": 2013,
      "sequenceType": "zwj",
      "active": true
    },
    {
      "index": 21,
      "row": 1,
      "column": 5,
      "x": 90,
      "y": 58,
      "width": 12,
      "height": 12,
      "key": "womanLiftingWeights",
      "name": "woman lifting weights",
      "emoji": "🏋️‍♀️",
      "codePoints": ["1F3CB", "FE0F", "200D", "2640", "FE0F"],
      "group": "People & Body",
      "subGroup": "person-sport",
      "order": 2019,
      "sequenceType": "zwj",
      "active": true
    },
    {
      "index": 22,
      "row": 1,
      "column": 6,
      "x": 106,
      "y": 58,
      "width": 12,
      "height": 12,
      "key": "personBiking",
      "name": "person biking",
      "emoji": "🚴",
      "codePoints": ["1F6B4"],
      "group": "People & Body",
      "subGroup": "person-sport",
      "order": 2025,
      "sequenceType": "single",
      "active": true
    },
    {
      "index": 23,
      "row": 1,
      "column": 7,
      "x": 122,
      "y": 58,
      "width": 12,
      "height": 12,
      "key": "manBiking",
      "name": "man biking",
      "emoji": "🚴‍♂️",
      "codePoints": ["1F6B4", "200D", "2642", "FE0F"],
      "group": "People & Body",
      "subGroup": "person-sport",
      "order": 2031,
      "sequenceType": "zwj",
      "active": true
    },
    {
      "index": 24,
      "row": 1,
      "column": 8,
      "x": 138,
      "y": 58,
      "width": 12,
      "height": 12,
      "key": "womanBiking",
      "name": "woman biking",
      "emoji": "🚴‍♀️",
      "codePoints": ["1F6B4", "200D", "2640", "FE0F"],
      "group": "People & Body",
      "subGroup": "person-sport",
      "order": 2037,
      "sequenceType": "zwj",
      "active": true
    },
    {
      "index": 25,
      "row": 1,
      "column": 9,
      "x": 154,
      "y": 58,
      "width": 12,
      "height": 12,
      "key": "personMountainBiking",
      "name": "person mountain biking",
      "emoji": "🚵",
      "codePoints": ["1F6B5"],
      "group": "People & Body",
      "subGroup": "person-sport",
      "order": 2043,
      "sequenceType": "single",
      "active": true
    },
    {
      "index": 26,
      "row": 1,
      "column": 10,
      "x": 170,
      "y": 58,
      "width": 12,
      "height": 12,
      "key": "manMountainBiking",
      "name": "man mountain biking",
      "emoji": "🚵‍♂️",
      "codePoints": ["1F6B5", "200D", "2642", "FE0F"],
      "group": "People & Body",
      "subGroup": "person-sport",
      "order": 2049,
      "sequenceType": "zwj",
      "active": true
    },
    {
      "index": 27,
      "row": 1,
      "column": 11,
      "x": 186,
      "y": 58,
      "width": 12,
      "height": 12,
      "key": "womanMountainBiking",
      "name": "woman mountain biking",
      "emoji": "🚵‍♀️",
      "codePoints": ["1F6B5", "200D", "2640", "FE0F"],
      "group": "People & Body",
      "subGroup": "person-sport",
      "order": 2055,
      "sequenceType": "zwj",
      "active": true
    },
    {
      "index": 28,
      "row": 1,
      "column": 12,
      "x": 202,
      "y": 58,
      "width": 12,
      "height": 12,
      "key": "personCartwheeling",
      "name": "person cartwheeling",
      "emoji": "🤸",
      "codePoints": ["1F938"],
      "group": "People & Body",
      "subGroup": "person-sport",
      "order": 2061,
      "sequenceType": "single",
      "active": true
    },
    {
      "index": 29,
      "row": 1,
      "column": 13,
      "x": 218,
      "y": 58,
      "width": 12,
      "height": 12,
      "key": "manCartwheeling",
      "name": "man cartwheeling",
      "emoji": "🤸‍♂️",
      "codePoints": ["1F938", "200D", "2642", "FE0F"],
      "group": "People & Body",
      "subGroup": "person-sport",
      "order": 2067,
      "sequenceType": "zwj",
      "active": true
    },
    {
      "index": 30,
      "row": 1,
      "column": 14,
      "x": 234,
      "y": 58,
      "width": 12,
      "height": 12,
      "key": "womanCartwheeling",
      "name": "woman cartwheeling",
      "emoji": "🤸‍♀️",
      "codePoints": ["1F938", "200D", "2640", "FE0F"],
      "group": "People & Body",
      "subGroup": "person-sport",
      "order": 2073,
      "sequenceType": "zwj",
      "active": true
    },
    {
      "index": 31,
      "row": 1,
      "column": 15,
      "x": 250,
      "y": 58,
      "width": 12,
      "height": 12,
      "key": "peopleWrestling",
      "name": "people wrestling",
      "emoji": "🤼",
      "codePoints": ["1F93C"],
      "group": "People & Body",
      "subGroup": "person-sport",
      "order": 2079,
      "sequenceType": "single",
      "active": true
    },
    {
      "index": 32,
      "row": 2,
      "column": 0,
      "x": 10,
      "y": 74,
      "width": 12,
      "height": 12,
      "key": "menWrestling",
      "name": "men wrestling",
      "emoji": "🤼‍♂️",
      "codePoints": ["1F93C", "200D", "2642", "FE0F"],
      "group": "People & Body",
      "subGroup": "person-sport",
      "order": 2085,
      "sequenceType": "zwj",
      "active": true
    },
    {
      "index": 33,
      "row": 2,
      "column": 1,
      "x": 26,
      "y": 74,
      "width": 12,
      "height": 12,
      "key": "womenWrestling",
      "name": "women wrestling",
      "emoji": "🤼‍♀️",
      "codePoints": ["1F93C", "200D", "2640", "FE0F"],
      "group": "People & Body",
      "subGroup": "person-sport",
      "order": 2091,
      "sequenceType": "zwj",
      "active": true
    },
    {
      "index": 34,
      "row": 2,
      "column": 2,
      "x": 42,
      "y": 74,
      "width": 12,
      "height": 12,
      "key": "personPlayingWaterPolo",
      "name": "person playing water polo",
      "emoji": "🤽",
      "codePoints": ["1F93D"],
      "group": "People & Body",
      "subGroup": "person-sport",
      "order": 2157,
      "sequenceType": "single",
      "active": true
    },
    {
      "index": 35,
      "row": 2,
      "column": 3,
      "x": 58,
      "y": 74,
      "width": 12,
      "height": 12,
      "key": "manPlayingWaterPolo",
      "name": "man playing water polo",
      "emoji": "🤽‍♂️",
      "codePoints": ["1F93D", "200D", "2642", "FE0F"],
      "group": "People & Body",
      "subGroup": "person-sport",
      "order": 2163,
      "sequenceType": "zwj",
      "active": true
    },
    {
      "index": 36,
      "row": 2,
      "column": 4,
      "x": 74,
      "y": 74,
      "width": 12,
      "height": 12,
      "key": "womanPlayingWaterPolo",
      "name": "woman playing water polo",
      "emoji": "🤽‍♀️",
      "codePoints": ["1F93D", "200D", "2640", "FE0F"],
      "group": "People & Body",
      "subGroup": "person-sport",
      "order": 2169,
      "sequenceType": "zwj",
      "active": true
    },
    {
      "index": 37,
      "row": 2,
      "column": 5,
      "x": 90,
      "y": 74,
      "width": 12,
      "height": 12,
      "key": "personPlayingHandball",
      "name": "person playing handball",
      "emoji": "🤾",
      "codePoints": ["1F93E"],
      "group": "People & Body",
      "subGroup": "person-sport",
      "order": 2175,
      "sequenceType": "single",
      "active": true
    },
    {
      "index": 38,
      "row": 2,
      "column": 6,
      "x": 106,
      "y": 74,
      "width": 12,
      "height": 12,
      "key": "manPlayingHandball",
      "name": "man playing handball",
      "emoji": "🤾‍♂️",
      "codePoints": ["1F93E", "200D", "2642", "FE0F"],
      "group": "People & Body",
      "subGroup": "person-sport",
      "order": 2181,
      "sequenceType": "zwj",
      "active": true
    },
    {
      "index": 39,
      "row": 2,
      "column": 7,
      "x": 122,
      "y": 74,
      "width": 12,
      "height": 12,
      "key": "womanPlayingHandball",
      "name": "woman playing handball",
      "emoji": "🤾‍♀️",
      "codePoints": ["1F93E", "200D", "2640", "FE0F"],
      "group": "People & Body",
      "subGroup": "person-sport",
      "order": 2187,
      "sequenceType": "zwj",
      "active": true
    },
    {
      "index": 40,
      "row": 2,
      "column": 8,
      "x": 138,
      "y": 74,
      "width": 12,
      "height": 12,
      "key": "personJuggling",
      "name": "person juggling",
      "emoji": "🤹",
      "codePoints": ["1F939"],
      "group": "People & Body",
      "subGroup": "person-sport",
      "order": 2193,
      "sequenceType": "single",
      "active": true
    },
    {
      "index": 41,
      "row": 2,
      "column": 9,
      "x": 154,
      "y": 74,
      "width": 12,
      "height": 12,
      "key": "manJuggling",
      "name": "man juggling",
      "emoji": "🤹‍♂️",
      "codePoints": ["1F939", "200D", "2642", "FE0F"],
      "group": "People & Body",
      "subGroup": "person-sport",
      "order": 2199,
      "sequenceType": "zwj",
      "active": true
    },
    {
      "index": 42,
      "row": 2,
      "column": 10,
      "x": 170,
      "y": 74,
      "width": 12,
      "height": 12,
      "key": "womanJuggling",
      "name": "woman juggling",
      "emoji": "🤹‍♀️",
      "codePoints": ["1F939", "200D", "2640", "FE0F"],
      "group": "People & Body",
      "subGroup": "person-sport",
      "order": 2205,
      "sequenceType": "zwj",
      "active": true
    }
  ]
}
