{
  "title": "Explorador de emoji",
  "matches": "coincidencias",
  "searchPlaceholder": "Buscar emoji, p. ej., cerveza o corazón",
  "languageNotLoaded": "Idioma no cargado",
  "noLanguagePack": "Sin paquete de idioma",
  "filtersLong": "Filtrar por categoría, versión y modificadores",
  "filters": "Filtros",
  "group": "Grupo",
  "subgroup": "Subgrupo",
  "versionFilter": "Filtro de versión",
  "emojiVersion": "Versión de emoji",
  "skinTone": "Tono de piel",
  "hair": "Cabello",
  "browse": "Explorar",
  "groups": "Grupos",
  "unicode": "Unicode",
  "sequences": "Secuencias",
  "localizedSearch": "Búsqueda localizada",
  "chooseLanguage": "Elige un idioma de búsqueda",
  "chooseLanguageDescription": "Elige un idioma para buscar emoji.",
  "throughSelectedVersion": "Todas hasta la versión seleccionada",
  "selectedVersionOnly": "Solo la versión seleccionada",
  "dark": "Oscuro",
  "mediumDark": "Medio oscuro",
  "medium": "Medio",
  "mediumLight": "Medio claro",
  "light": "Claro",
  "red": "Rojo",
  "curly": "Rizado",
  "bald": "Calvo",
  "white": "Blanco",
  "all": "Todos",
  "expected": "previsto",
  "updated": "actualizado",
  "africa": "África",
  "asia": "Asia",
  "europe": "Europa",
  "northAmerica": "América del Norte",
  "southAmerica": "América del Sur",
  "oceania": "Oceanía",
  "otherFlags": "Otras banderas",
  "accessories": "Accesorios",
  "clothing": "Ropa",
  "hatsHeadwear": "Sombreros y accesorios para la cabeza",
  "shoes": "Zapatos",
  "couplesWithHeart": "Parejas con corazón",
  "families": "Familias",
  "holdingHands": "Tomados de la mano",
  "kissingCouples": "Parejas besándose",
  "adults": "Adultos",
  "children": "Niños",
  "keywords": "palabras clave",
  "emojiDetails": "Detalles del emoji",
  "released": "publicado",
  "englishName": "Nombre en inglés",
  "introduced": "Introducido",
  "codePoints": "Puntos de código",
  "sequenceType": "Tipo de secuencia",
  "builtFrom": "Compuesto por",
  "result": "Resultado",
  "zeroWidthJoiner": "Conector de ancho cero",
  "emojiPresentation": "Selector de presentación de emoji",
  "textPresentation": "Selector de presentación de texto",
  "combiningKeycap": "Tecla combinada",
  "tagCharacter": "Carácter de etiqueta",
  "cancelTag": "Fin de etiqueta",
  "tagAbbreviation": "ETIQ.",
  "cancelTagAbbreviation": "FIN",
  "keycapAbbreviation": "TECLA",
  "viewEmoji": "Ver emoji",
  "showFullSequence": "Mostrar secuencia completa",
  "showCondensedSequence": "Mostrar secuencia condensada",
  "regionalIndicator": "Indicador regional",
  "qualification": "Calificación",
  "copy": "Copiar",
  "copyEmoji": "Copiar emoji",
  "copyKey": "Copiar clave",
  "copyEscape": "Copiar escape",
  "copyCodePoints": "Copiar puntos de código",
  "viewCode": "Ver código",
  "codeExample": "Ejemplo de código",
  "backToEmoji": "Volver al emoji",
  "copyCode": "Copiar código",
  "copyLink": "Copiar enlace",
  "savedEmoji": "Emojis guardados",
  "favorites": "Favoritos",
  "recentlyCopied": "Copiados recientemente",
  "noFavorites": "Tus emojis favoritos aparecerán aquí.",
  "noRecentlyCopied": "Los emojis copiados aparecerán aquí.",
  "addFavorite": "Añadir a favoritos",
  "removeFavorite": "Quitar de favoritos",
  "keyboardShortcuts": "Atajos de teclado",
  "shortcutSearch": "Enfocar la búsqueda",
  "shortcutNavigate": "Navegar por los emojis",
  "shortcutOpen": "Abrir el emoji seleccionado",
  "shortcutClose": "Cerrar un diálogo o borrar la búsqueda",
  "shortcutHelp": "Abrir la ayuda del teclado",
  "sequenceSingle": "Emoji individual",
  "sequenceModifier": "Secuencia modificadora",
  "sequenceZwj": "Secuencia ZWJ",
  "sequenceFlag": "Secuencia de bandera",
  "sequenceKeycap": "Secuencia de tecla",
  "sequenceTag": "Secuencia de etiquetas",
  "fullyQualified": "Totalmente calificado",
  "minimallyQualified": "Calificación mínima",
  "unqualified": "Sin calificar",
  "loadingEmoji": "Cargando emojis…",
  "loadingVersions": "Cargando versiones…",
  "loadingLanguage": "Cargando idioma…",
  "offlineStatus": "Sin conexión — mostrando datos guardados",
  "aboutTitle": "Busca y explora emojis de Unicode",
  "aboutDescription": "Explora miles de emojis por nombres y palabras clave localizados, categorías y subgrupos de Unicode, versión de lanzamiento, modificadores y tipo de secuencia.",
  "clearAll": "Borrar todo",
  "previousVersion": "Versión anterior",
  "nextVersion": "Versión siguiente",
  "noResults": "No se encontraron emojis",
  "noResultsDescription": "Prueba a eliminar un término de búsqueda o filtro.",
  "clearSearch": "Borrar búsqueda",
  "resetFilters": "Restablecer filtros",
  "previousEmoji": "Emoji anterior",
  "nextEmoji": "Emoji siguiente",
  "onlyVersion": "Solo",
  "throughVersion": "Hasta",
  "gender": "Género",
  "male": "Masculino",
  "female": "Femenino",
  "neutral": "Neutro",
  "filterEmoji": "Filtrar emojis",
  "searchEmoji": "Buscar emojis",
  "skipToResults": "Saltar a los resultados de emojis",
  "emojiResults": "Resultados de emojis",
  "emojiBrowseOrder": "Orden de exploración de emojis",
  "chooseBrowseOrder": "Elegir el orden de exploración de emojis",
  "close": "Cerrar",
  "emojiCopied": "Emoji copiado al portapapeles.",
  "keyCopied": "Clave del emoji copiada al portapapeles.",
  "escapeCopied": "Secuencia de escape copiada al portapapeles.",
  "codePointsCopied": "Puntos de código copiados al portapapeles.",
  "codeCopied": "Código copiado al portapapeles.",
  "linkCopied": "Enlace copiado al portapapeles.",
  "copiedToClipboard": "Copiado al portapapeles.",
  "copyFailed": "No se pudo copiar al portapapeles."
}
