{
  "schemaVersion": 1,
  "id": "base-007",
  "image": "base-007.png",
  "cellSize": 16,
  "columns": 16,
  "rows": 16,
  "capacity": 256,
  "entries": [
    {
      "index": 0,
      "row": 0,
      "column": 0,
      "x": 0,
      "y": 0,
      "width": 16,
      "height": 16,
      "key": "flagMyanmarBurma",
      "name": "flag: Myanmar (Burma)",
      "emoji": "🇲🇲",
      "codePoints": ["1F1F2", "1F1F2"],
      "group": "Flags",
      "subGroup": "country-flag",
      "order": 3843,
      "sequenceType": "flag",
      "active": true
    },
    {
      "index": 1,
      "row": 0,
      "column": 1,
      "x": 16,
      "y": 0,
      "width": 16,
      "height": 16,
      "key": "flagMongolia",
      "name": "flag: Mongolia",
      "emoji": "🇲🇳",
      "codePoints": ["1F1F2", "1F1F3"],
      "group": "Flags",
      "subGroup": "country-flag",
      "order": 3844,
      "sequenceType": "flag",
      "active": true
    },
    {
      "index": 2,
      "row": 0,
      "column": 2,
      "x": 32,
      "y": 0,
      "width": 16,
      "height": 16,
      "key": "flagMacaoSARChina",
      "name": "flag: Macao SAR China",
      "emoji": "🇲🇴",
      "codePoints": ["1F1F2", "1F1F4"],
      "group": "Flags",
      "subGroup": "country-flag",
      "order": 3845,
      "sequenceType": "flag",
      "active": true
    },
    {
      "index": 3,
      "row": 0,
      "column": 3,
      "x": 48,
      "y": 0,
      "width": 16,
      "height": 16,
      "key": "flagNorthernMarianaIslands",
      "name": "flag: Northern Mariana Islands",
      "emoji": "🇲🇵",
      "codePoints": ["1F1F2", "1F1F5"],
      "group": "Flags",
      "subGroup": "country-flag",
      "order": 3846,
      "sequenceType": "flag",
      "active": true
    },
    {
      "index": 4,
      "row": 0,
      "column": 4,
      "x": 64,
      "y": 0,
      "width": 16,
      "height": 16,
      "key": "flagMartinique",
      "name": "flag: Martinique",
      "emoji": "🇲🇶",
      "codePoints": ["1F1F2", "1F1F6"],
      "group": "Flags",
      "subGroup": "country-flag",
      "order": 3847,
      "sequenceType": "flag",
      "active": true
    },
    {
      "index": 5,
      "row": 0,
      "column": 5,
      "x": 80,
      "y": 0,
      "width": 16,
      "height": 16,
      "key": "flagMauritania",
      "name": "flag: Mauritania",
      "emoji": "🇲🇷",
      "codePoints": ["1F1F2", "1F1F7"],
      "group": "Flags",
      "subGroup": "country-flag",
      "order": 3848,
      "sequenceType": "flag",
      "active": true
    },
    {
      "index": 6,
      "row": 0,
      "column": 6,
      "x": 96,
      "y": 0,
      "width": 16,
      "height": 16,
      "key": "flagMontserrat",
      "name": "flag: Montserrat",
      "emoji": "🇲🇸",
      "codePoints": ["1F1F2", "1F1F8"],
      "group": "Flags",
      "subGroup": "country-flag",
      "order": 3849,
      "sequenceType": "flag",
      "active": true
    },
    {
      "index": 7,
      "row": 0,
      "column": 7,
      "x": 112,
      "y": 0,
      "width": 16,
      "height": 16,
      "key": "flagMalta",
      "name": "flag: Malta",
      "emoji": "🇲🇹",
      "codePoints": ["1F1F2", "1F1F9"],
      "group": "Flags",
      "subGroup": "country-flag",
      "order": 3850,
      "sequenceType": "flag",
      "active": true
    },
    {
      "index": 8,
      "row": 0,
      "column": 8,
      "x": 128,
      "y": 0,
      "width": 16,
      "height": 16,
      "key": "flagMauritius",
      "name": "flag: Mauritius",
      "emoji": "🇲🇺",
      "codePoints": ["1F1F2", "1F1FA"],
      "group": "Flags",
      "subGroup": "country-flag",
      "order": 3851,
      "sequenceType": "flag",
      "active": true
    },
    {
      "index": 9,
      "row": 0,
      "column": 9,
      "x": 144,
      "y": 0,
      "width": 16,
      "height": 16,
      "key": "flagMaldives",
      "name": "flag: Maldives",
      "emoji": "🇲🇻",
      "codePoints": ["1F1F2", "1F1FB"],
      "group": "Flags",
      "subGroup": "country-flag",
      "order": 3852,
      "sequenceType": "flag",
      "active": true
    },
    {
      "index": 10,
      "row": 0,
      "column": 10,
      "x": 160,
      "y": 0,
      "width": 16,
      "height": 16,
      "key": "flagMalawi",
      "name": "flag: Malawi",
      "emoji": "🇲🇼",
      "codePoints": ["1F1F2", "1F1FC"],
      "group": "Flags",
      "subGroup": "country-flag",
      "order": 3853,
      "sequenceType": "flag",
      "active": true
    },
    {
      "index": 11,
      "row": 0,
      "column": 11,
      "x": 176,
      "y": 0,
      "width": 16,
      "height": 16,
      "key": "flagMexico",
      "name": "flag: Mexico",
      "emoji": "🇲🇽",
      "codePoints": ["1F1F2", "1F1FD"],
      "group": "Flags",
      "subGroup": "country-flag",
      "order": 3854,
      "sequenceType": "flag",
      "active": true
    },
    {
      "index": 12,
      "row": 0,
      "column": 12,
      "x": 192,
      "y": 0,
      "width": 16,
      "height": 16,
      "key": "flagMalaysia",
      "name": "flag: Malaysia",
      "emoji": "🇲🇾",
      "codePoints": ["1F1F2", "1F1FE"],
      "group": "Flags",
      "subGroup": "country-flag",
      "order": 3855,
      "sequenceType": "flag",
      "active": true
    },
    {
      "index": 13,
      "row": 0,
      "column": 13,
      "x": 208,
      "y": 0,
      "width": 16,
      "height": 16,
      "key": "flagMozambique",
      "name": "flag: Mozambique",
      "emoji": "🇲🇿",
      "codePoints": ["1F1F2", "1F1FF"],
      "group": "Flags",
      "subGroup": "country-flag",
      "order": 3856,
      "sequenceType": "flag",
      "active": true
    },
    {
      "index": 14,
      "row": 0,
      "column": 14,
      "x": 224,
      "y": 0,
      "width": 16,
      "height": 16,
      "key": "flagNamibia",
      "name": "flag: Namibia",
      "emoji": "🇳🇦",
      "codePoints": ["1F1F3", "1F1E6"],
      "group": "Flags",
      "subGroup": "country-flag",
      "order": 3857,
      "sequenceType": "flag",
      "active": true
    },
    {
      "index": 15,
      "row": 0,
      "column": 15,
      "x": 240,
      "y": 0,
      "width": 16,
      "height": 16,
      "key": "flagNewCaledonia",
      "name": "flag: New Caledonia",
      "emoji": "🇳🇨",
      "codePoints": ["1F1F3", "1F1E8"],
      "group": "Flags",
      "subGroup": "country-flag",
      "order": 3858,
      "sequenceType": "flag",
      "active": true
    },
    {
      "index": 16,
      "row": 1,
      "column": 0,
      "x": 0,
      "y": 16,
      "width": 16,
      "height": 16,
      "key": "flagNiger",
      "name": "flag: Niger",
      "emoji": "🇳🇪",
      "codePoints": ["1F1F3", "1F1EA"],
      "group": "Flags",
      "subGroup": "country-flag",
      "order": 3859,
      "sequenceType": "flag",
      "active": true
    },
    {
      "index": 17,
      "row": 1,
      "column": 1,
      "x": 16,
      "y": 16,
      "width": 16,
      "height": 16,
      "key": "flagNorfolkIsland",
      "name": "flag: Norfolk Island",
      "emoji": "🇳🇫",
      "codePoints": ["1F1F3", "1F1EB"],
      "group": "Flags",
      "subGroup": "country-flag",
      "order": 3860,
      "sequenceType": "flag",
      "active": true
    },
    {
      "index": 18,
      "row": 1,
      "column": 2,
      "x": 32,
      "y": 16,
      "width": 16,
      "height": 16,
      "key": "flagNigeria",
      "name": "flag: Nigeria",
      "emoji": "🇳🇬",
      "codePoints": ["1F1F3", "1F1EC"],
      "group": "Flags",
      "subGroup": "country-flag",
      "order": 3861,
      "sequenceType": "flag",
      "active": true
    },
    {
      "index": 19,
      "row": 1,
      "column": 3,
      "x": 48,
      "y": 16,
      "width": 16,
      "height": 16,
      "key": "flagNicaragua",
      "name": "flag: Nicaragua",
      "emoji": "🇳🇮",
      "codePoints": ["1F1F3", "1F1EE"],
      "group": "Flags",
      "subGroup": "country-flag",
      "order": 3862,
      "sequenceType": "flag",
      "active": true
    },
    {
      "index": 20,
      "row": 1,
      "column": 4,
      "x": 64,
      "y": 16,
      "width": 16,
      "height": 16,
      "key": "flagNetherlands",
      "name": "flag: Netherlands",
      "emoji": "🇳🇱",
      "codePoints": ["1F1F3", "1F1F1"],
      "group": "Flags",
      "subGroup": "country-flag",
      "order": 3863,
      "sequenceType": "flag",
      "active": true
    },
    {
      "index": 21,
      "row": 1,
      "column": 5,
      "x": 80,
      "y": 16,
      "width": 16,
      "height": 16,
      "key": "flagNorway",
      "name": "flag: Norway",
      "emoji": "🇳🇴",
      "codePoints": ["1F1F3", "1F1F4"],
      "group": "Flags",
      "subGroup": "country-flag",
      "order": 3864,
      "sequenceType": "flag",
      "active": true
    },
    {
      "index": 22,
      "row": 1,
      "column": 6,
      "x": 96,
      "y": 16,
      "width": 16,
      "height": 16,
      "key": "flagNepal",
      "name": "flag: Nepal",
      "emoji": "🇳🇵",
      "codePoints": ["1F1F3", "1F1F5"],
      "group": "Flags",
      "subGroup": "country-flag",
      "order": 3865,
      "sequenceType": "flag",
      "active": true
    },
    {
      "index": 23,
      "row": 1,
      "column": 7,
      "x": 112,
      "y": 16,
      "width": 16,
      "height": 16,
      "key": "flagNauru",
      "name": "flag: Nauru",
      "emoji": "🇳🇷",
      "codePoints": ["1F1F3", "1F1F7"],
      "group": "Flags",
      "subGroup": "country-flag",
      "order": 3866,
      "sequenceType": "flag",
      "active": true
    },
    {
      "index": 24,
      "row": 1,
      "column": 8,
      "x": 128,
      "y": 16,
      "width": 16,
      "height": 16,
      "key": "flagNiue",
      "name": "flag: Niue",
      "emoji": "🇳🇺",
      "codePoints": ["1F1F3", "1F1FA"],
      "group": "Flags",
      "subGroup": "country-flag",
      "order": 3867,
      "sequenceType": "flag",
      "active": true
    },
    {
      "index": 25,
      "row": 1,
      "column": 9,
      "x": 144,
      "y": 16,
      "width": 16,
      "height": 16,
      "key": "flagNewZealand",
      "name": "flag: New Zealand",
      "emoji": "🇳🇿",
      "codePoints": ["1F1F3", "1F1FF"],
      "group": "Flags",
      "subGroup": "country-flag",
      "order": 3868,
      "sequenceType": "flag",
      "active": true
    },
    {
      "index": 26,
      "row": 1,
      "column": 10,
      "x": 160,
      "y": 16,
      "width": 16,
      "height": 16,
      "key": "flagOman",
      "name": "flag: Oman",
      "emoji": "🇴🇲",
      "codePoints": ["1F1F4", "1F1F2"],
      "group": "Flags",
      "subGroup": "country-flag",
      "order": 3869,
      "sequenceType": "flag",
      "active": true
    },
    {
      "index": 27,
      "row": 1,
      "column": 11,
      "x": 176,
      "y": 16,
      "width": 16,
      "height": 16,
      "key": "flagPanama",
      "name": "flag: Panama",
      "emoji": "🇵🇦",
      "codePoints": ["1F1F5", "1F1E6"],
      "group": "Flags",
      "subGroup": "country-flag",
      "order": 3870,
      "sequenceType": "flag",
      "active": true
    },
    {
      "index": 28,
      "row": 1,
      "column": 12,
      "x": 192,
      "y": 16,
      "width": 16,
      "height": 16,
      "key": "flagPeru",
      "name": "flag: Peru",
      "emoji": "🇵🇪",
      "codePoints": ["1F1F5", "1F1EA"],
      "group": "Flags",
      "subGroup": "country-flag",
      "order": 3871,
      "sequenceType": "flag",
      "active": true
    },
    {
      "index": 29,
      "row": 1,
      "column": 13,
      "x": 208,
      "y": 16,
      "width": 16,
      "height": 16,
      "key": "flagFrenchPolynesia",
      "name": "flag: French Polynesia",
      "emoji": "🇵🇫",
      "codePoints": ["1F1F5", "1F1EB"],
      "group": "Flags",
      "subGroup": "country-flag",
      "order": 3872,
      "sequenceType": "flag",
      "active": true
    },
    {
      "index": 30,
      "row": 1,
      "column": 14,
      "x": 224,
      "y": 16,
      "width": 16,
      "height": 16,
      "key": "flagPapuaNewGuinea",
      "name": "flag: Papua New Guinea",
      "emoji": "🇵🇬",
      "codePoints": ["1F1F5", "1F1EC"],
      "group": "Flags",
      "subGroup": "country-flag",
      "order": 3873,
      "sequenceType": "flag",
      "active": true
    },
    {
      "index": 31,
      "row": 1,
      "column": 15,
      "x": 240,
      "y": 16,
      "width": 16,
      "height": 16,
      "key": "flagPhilippines",
      "name": "flag: Philippines",
      "emoji": "🇵🇭",
      "codePoints": ["1F1F5", "1F1ED"],
      "group": "Flags",
      "subGroup": "country-flag",
      "order": 3874,
      "sequenceType": "flag",
      "active": true
    },
    {
      "index": 32,
      "row": 2,
      "column": 0,
      "x": 0,
      "y": 32,
      "width": 16,
      "height": 16,
      "key": "flagPakistan",
      "name": "flag: Pakistan",
      "emoji": "🇵🇰",
      "codePoints": ["1F1F5", "1F1F0"],
      "group": "Flags",
      "subGroup": "country-flag",
      "order": 3875,
      "sequenceType": "flag",
      "active": true
    },
    {
      "index": 33,
      "row": 2,
      "column": 1,
      "x": 16,
      "y": 32,
      "width": 16,
      "height": 16,
      "key": "flagPoland",
      "name": "flag: Poland",
      "emoji": "🇵🇱",
      "codePoints": ["1F1F5", "1F1F1"],
      "group": "Flags",
      "subGroup": "country-flag",
      "order": 3876,
      "sequenceType": "flag",
      "active": true
    },
    {
      "index": 34,
      "row": 2,
      "column": 2,
      "x": 32,
      "y": 32,
      "width": 16,
      "height": 16,
      "key": "flagStPierreAndMiquelon",
      "name": "flag: St. Pierre & Miquelon",
      "emoji": "🇵🇲",
      "codePoints": ["1F1F5", "1F1F2"],
      "group": "Flags",
      "subGroup": "country-flag",
      "order": 3877,
      "sequenceType": "flag",
      "active": true
    },
    {
      "index": 35,
      "row": 2,
      "column": 3,
      "x": 48,
      "y": 32,
      "width": 16,
      "height": 16,
      "key": "flagPitcairnIslands",
      "name": "flag: Pitcairn Islands",
      "emoji": "🇵🇳",
      "codePoints": ["1F1F5", "1F1F3"],
      "group": "Flags",
      "subGroup": "country-flag",
      "order": 3878,
      "sequenceType": "flag",
      "active": true
    },
    {
      "index": 36,
      "row": 2,
      "column": 4,
      "x": 64,
      "y": 32,
      "width": 16,
      "height": 16,
      "key": "flagPuertoRico",
      "name": "flag: Puerto Rico",
      "emoji": "🇵🇷",
      "codePoints": ["1F1F5", "1F1F7"],
      "group": "Flags",
      "subGroup": "country-flag",
      "order": 3879,
      "sequenceType": "flag",
      "active": true
    },
    {
      "index": 37,
      "row": 2,
      "column": 5,
      "x": 80,
      "y": 32,
      "width": 16,
      "height": 16,
      "key": "flagPalestinianTerritories",
      "name": "flag: Palestinian Territories",
      "emoji": "🇵🇸",
      "codePoints": ["1F1F5", "1F1F8"],
      "group": "Flags",
      "subGroup": "country-flag",
      "order": 3880,
      "sequenceType": "flag",
      "active": true
    },
    {
      "index": 38,
      "row": 2,
      "column": 6,
      "x": 96,
      "y": 32,
      "width": 16,
      "height": 16,
      "key": "flagPortugal",
      "name": "flag: Portugal",
      "emoji": "🇵🇹",
      "codePoints": ["1F1F5", "1F1F9"],
      "group": "Flags",
      "subGroup": "country-flag",
      "order": 3881,
      "sequenceType": "flag",
      "active": true
    },
    {
      "index": 39,
      "row": 2,
      "column": 7,
      "x": 112,
      "y": 32,
      "width": 16,
      "height": 16,
      "key": "flagPalau",
      "name": "flag: Palau",
      "emoji": "🇵🇼",
      "codePoints": ["1F1F5", "1F1FC"],
      "group": "Flags",
      "subGroup": "country-flag",
      "order": 3882,
      "sequenceType": "flag",
      "active": true
    },
    {
      "index": 40,
      "row": 2,
      "column": 8,
      "x": 128,
      "y": 32,
      "width": 16,
      "height": 16,
      "key": "flagParaguay",
      "name": "flag: Paraguay",
      "emoji": "🇵🇾",
      "codePoints": ["1F1F5", "1F1FE"],
      "group": "Flags",
      "subGroup": "country-flag",
      "order": 3883,
      "sequenceType": "flag",
      "active": true
    },
    {
      "index": 41,
      "row": 2,
      "column": 9,
      "x": 144,
      "y": 32,
      "width": 16,
      "height": 16,
      "key": "flagQatar",
      "name": "flag: Qatar",
      "emoji": "🇶🇦",
      "codePoints": ["1F1F6", "1F1E6"],
      "group": "Flags",
      "subGroup": "country-flag",
      "order": 3884,
      "sequenceType": "flag",
      "active": true
    },
    {
      "index": 42,
      "row": 2,
      "column": 10,
      "x": 160,
      "y": 32,
      "width": 16,
      "height": 16,
      "key": "flagReunion",
      "name": "flag: Réunion",
      "emoji": "🇷🇪",
      "codePoints": ["1F1F7", "1F1EA"],
      "group": "Flags",
      "subGroup": "country-flag",
      "order": 3885,
      "sequenceType": "flag",
      "active": true
    },
    {
      "index": 43,
      "row": 2,
      "column": 11,
      "x": 176,
      "y": 32,
      "width": 16,
      "height": 16,
      "key": "flagRomania",
      "name": "flag: Romania",
      "emoji": "🇷🇴",
      "codePoints": ["1F1F7", "1F1F4"],
      "group": "Flags",
      "subGroup": "country-flag",
      "order": 3886,
      "sequenceType": "flag",
      "active": true
    },
    {
      "index": 44,
      "row": 2,
      "column": 12,
      "x": 192,
      "y": 32,
      "width": 16,
      "height": 16,
      "key": "flagSerbia",
      "name": "flag: Serbia",
      "emoji": "🇷🇸",
      "codePoints": ["1F1F7", "1F1F8"],
      "group": "Flags",
      "subGroup": "country-flag",
      "order": 3887,
      "sequenceType": "flag",
      "active": true
    },
    {
      "index": 45,
      "row": 2,
      "column": 13,
      "x": 208,
      "y": 32,
      "width": 16,
      "height": 16,
      "key": "flagRussia",
      "name": "flag: Russia",
      "emoji": "🇷🇺",
      "codePoints": ["1F1F7", "1F1FA"],
      "group": "Flags",
      "subGroup": "country-flag",
      "order": 3888,
      "sequenceType": "flag",
      "active": true
    },
    {
      "index": 46,
      "row": 2,
      "column": 14,
      "x": 224,
      "y": 32,
      "width": 16,
      "height": 16,
      "key": "flagRwanda",
      "name": "flag: Rwanda",
      "emoji": "🇷🇼",
      "codePoints": ["1F1F7", "1F1FC"],
      "group": "Flags",
      "subGroup": "country-flag",
      "order": 3889,
      "sequenceType": "flag",
      "active": true
    },
    {
      "index": 47,
      "row": 2,
      "column": 15,
      "x": 240,
      "y": 32,
      "width": 16,
      "height": 16,
      "key": "flagSaudiArabia",
      "name": "flag: Saudi Arabia",
      "emoji": "🇸🇦",
      "codePoints": ["1F1F8", "1F1E6"],
      "group": "Flags",
      "subGroup": "country-flag",
      "order": 3890,
      "sequenceType": "flag",
      "active": true
    },
    {
      "index": 48,
      "row": 3,
      "column": 0,
      "x": 0,
      "y": 48,
      "width": 16,
      "height": 16,
      "key": "flagSolomonIslands",
      "name": "flag: Solomon Islands",
      "emoji": "🇸🇧",
      "codePoints": ["1F1F8", "1F1E7"],
      "group": "Flags",
      "subGroup": "country-flag",
      "order": 3891,
      "sequenceType": "flag",
      "active": true
    },
    {
      "index": 49,
      "row": 3,
      "column": 1,
      "x": 16,
      "y": 48,
      "width": 16,
      "height": 16,
      "key": "flagSeychelles",
      "name": "flag: Seychelles",
      "emoji": "🇸🇨",
      "codePoints": ["1F1F8", "1F1E8"],
      "group": "Flags",
      "subGroup": "country-flag",
      "order": 3892,
      "sequenceType": "flag",
      "active": true
    },
    {
      "index": 50,
      "row": 3,
      "column": 2,
      "x": 32,
      "y": 48,
      "width": 16,
      "height": 16,
      "key": "flagSudan",
      "name": "flag: Sudan",
      "emoji": "🇸🇩",
      "codePoints": ["1F1F8", "1F1E9"],
      "group": "Flags",
      "subGroup": "country-flag",
      "order": 3893,
      "sequenceType": "flag",
      "active": true
    },
    {
      "index": 51,
      "row": 3,
      "column": 3,
      "x": 48,
      "y": 48,
      "width": 16,
      "height": 16,
      "key": "flagSweden",
      "name": "flag: Sweden",
      "emoji": "🇸🇪",
      "codePoints": ["1F1F8", "1F1EA"],
      "group": "Flags",
      "subGroup": "country-flag",
      "order": 3894,
      "sequenceType": "flag",
      "active": true
    },
    {
      "index": 52,
      "row": 3,
      "column": 4,
      "x": 64,
      "y": 48,
      "width": 16,
      "height": 16,
      "key": "flagSingapore",
      "name": "flag: Singapore",
      "emoji": "🇸🇬",
      "codePoints": ["1F1F8", "1F1EC"],
      "group": "Flags",
      "subGroup": "country-flag",
      "order": 3895,
      "sequenceType": "flag",
      "active": true
    },
    {
      "index": 53,
      "row": 3,
      "column": 5,
      "x": 80,
      "y": 48,
      "width": 16,
      "height": 16,
      "key": "flagStHelena",
      "name": "flag: St. Helena",
      "emoji": "🇸🇭",
      "codePoints": ["1F1F8", "1F1ED"],
      "group": "Flags",
      "subGroup": "country-flag",
      "order": 3896,
      "sequenceType": "flag",
      "active": true
    },
    {
      "index": 54,
      "row": 3,
      "column": 6,
      "x": 96,
      "y": 48,
      "width": 16,
      "height": 16,
      "key": "flagSlovenia",
      "name": "flag: Slovenia",
      "emoji": "🇸🇮",
      "codePoints": ["1F1F8", "1F1EE"],
      "group": "Flags",
      "subGroup": "country-flag",
      "order": 3897,
      "sequenceType": "flag",
      "active": true
    },
    {
      "index": 55,
      "row": 3,
      "column": 7,
      "x": 112,
      "y": 48,
      "width": 16,
      "height": 16,
      "key": "flagSvalbardAndJanMayen",
      "name": "flag: Svalbard & Jan Mayen",
      "emoji": "🇸🇯",
      "codePoints": ["1F1F8", "1F1EF"],
      "group": "Flags",
      "subGroup": "country-flag",
      "order": 3898,
      "sequenceType": "flag",
      "active": true
    },
    {
      "index": 56,
      "row": 3,
      "column": 8,
      "x": 128,
      "y": 48,
      "width": 16,
      "height": 16,
      "key": "flagSlovakia",
      "name": "flag: Slovakia",
      "emoji": "🇸🇰",
      "codePoints": ["1F1F8", "1F1F0"],
      "group": "Flags",
      "subGroup": "country-flag",
      "order": 3899,
      "sequenceType": "flag",
      "active": true
    },
    {
      "index": 57,
      "row": 3,
      "column": 9,
      "x": 144,
      "y": 48,
      "width": 16,
      "height": 16,
      "key": "flagSierraLeone",
      "name": "flag: Sierra Leone",
      "emoji": "🇸🇱",
      "codePoints": ["1F1F8", "1F1F1"],
      "group": "Flags",
      "subGroup": "country-flag",
      "order": 3900,
      "sequenceType": "flag",
      "active": true
    },
    {
      "index": 58,
      "row": 3,
      "column": 10,
      "x": 160,
      "y": 48,
      "width": 16,
      "height": 16,
      "key": "flagSanMarino",
      "name": "flag: San Marino",
      "emoji": "🇸🇲",
      "codePoints": ["1F1F8", "1F1F2"],
      "group": "Flags",
      "subGroup": "country-flag",
      "order": 3901,
      "sequenceType": "flag",
      "active": true
    },
    {
      "index": 59,
      "row": 3,
      "column": 11,
      "x": 176,
      "y": 48,
      "width": 16,
      "height": 16,
      "key": "flagSenegal",
      "name": "flag: Senegal",
      "emoji": "🇸🇳",
      "codePoints": ["1F1F8", "1F1F3"],
      "group": "Flags",
      "subGroup": "country-flag",
      "order": 3902,
      "sequenceType": "flag",
      "active": true
    },
    {
      "index": 60,
      "row": 3,
      "column": 12,
      "x": 192,
      "y": 48,
      "width": 16,
      "height": 16,
      "key": "flagSomalia",
      "name": "flag: Somalia",
      "emoji": "🇸🇴",
      "codePoints": ["1F1F8", "1F1F4"],
      "group": "Flags",
      "subGroup": "country-flag",
      "order": 3903,
      "sequenceType": "flag",
      "active": true
    },
    {
      "index": 61,
      "row": 3,
      "column": 13,
      "x": 208,
      "y": 48,
      "width": 16,
      "height": 16,
      "key": "flagSuriname",
      "name": "flag: Suriname",
      "emoji": "🇸🇷",
      "codePoints": ["1F1F8", "1F1F7"],
      "group": "Flags",
      "subGroup": "country-flag",
      "order": 3904,
      "sequenceType": "flag",
      "active": true
    },
    {
      "index": 62,
      "row": 3,
      "column": 14,
      "x": 224,
      "y": 48,
      "width": 16,
      "height": 16,
      "key": "flagSouthSudan",
      "name": "flag: South Sudan",
      "emoji": "🇸🇸",
      "codePoints": ["1F1F8", "1F1F8"],
      "group": "Flags",
      "subGroup": "country-flag",
      "order": 3905,
      "sequenceType": "flag",
      "active": true
    },
    {
      "index": 63,
      "row": 3,
      "column": 15,
      "x": 240,
      "y": 48,
      "width": 16,
      "height": 16,
      "key": "flagSaoTomeAndPrincipe",
      "name": "flag: São Tomé & Príncipe",
      "emoji": "🇸🇹",
      "codePoints": ["1F1F8", "1F1F9"],
      "group": "Flags",
      "subGroup": "country-flag",
      "order": 3906,
      "sequenceType": "flag",
      "active": true
    },
    {
      "index": 64,
      "row": 4,
      "column": 0,
      "x": 0,
      "y": 64,
      "width": 16,
      "height": 16,
      "key": "flagElSalvador",
      "name": "flag: El Salvador",
      "emoji": "🇸🇻",
      "codePoints": ["1F1F8", "1F1FB"],
      "group": "Flags",
      "subGroup": "country-flag",
      "order": 3907,
      "sequenceType": "flag",
      "active": true
    },
    {
      "index": 65,
      "row": 4,
      "column": 1,
      "x": 16,
      "y": 64,
      "width": 16,
      "height": 16,
      "key": "flagSintMaarten",
      "name": "flag: Sint Maarten",
      "emoji": "🇸🇽",
      "codePoints": ["1F1F8", "1F1FD"],
      "group": "Flags",
      "subGroup": "country-flag",
      "order": 3908,
      "sequenceType": "flag",
      "active": true
    },
    {
      "index": 66,
      "row": 4,
      "column": 2,
      "x": 32,
      "y": 64,
      "width": 16,
      "height": 16,
      "key": "flagSyria",
      "name": "flag: Syria",
      "emoji": "🇸🇾",
      "codePoints": ["1F1F8", "1F1FE"],
      "group": "Flags",
      "subGroup": "country-flag",
      "order": 3909,
      "sequenceType": "flag",
      "active": true
    },
    {
      "index": 67,
      "row": 4,
      "column": 3,
      "x": 48,
      "y": 64,
      "width": 16,
      "height": 16,
      "key": "flagEswatini",
      "name": "flag: Eswatini",
      "emoji": "🇸🇿",
      "codePoints": ["1F1F8", "1F1FF"],
      "group": "Flags",
      "subGroup": "country-flag",
      "order": 3910,
      "sequenceType": "flag",
      "active": true
    },
    {
      "index": 68,
      "row": 4,
      "column": 4,
      "x": 64,
      "y": 64,
      "width": 16,
      "height": 16,
      "key": "flagTristanDaCunha",
      "name": "flag: Tristan da Cunha",
      "emoji": "🇹🇦",
      "codePoints": ["1F1F9", "1F1E6"],
      "group": "Flags",
      "subGroup": "country-flag",
      "order": 3911,
      "sequenceType": "flag",
      "active": true
    },
    {
      "index": 69,
      "row": 4,
      "column": 5,
      "x": 80,
      "y": 64,
      "width": 16,
      "height": 16,
      "key": "flagTurksAndCaicosIslands",
      "name": "flag: Turks & Caicos Islands",
      "emoji": "🇹🇨",
      "codePoints": ["1F1F9", "1F1E8"],
      "group": "Flags",
      "subGroup": "country-flag",
      "order": 3912,
      "sequenceType": "flag",
      "active": true
    },
    {
      "index": 70,
      "row": 4,
      "column": 6,
      "x": 96,
      "y": 64,
      "width": 16,
      "height": 16,
      "key": "flagChad",
      "name": "flag: Chad",
      "emoji": "🇹🇩",
      "codePoints": ["1F1F9", "1F1E9"],
      "group": "Flags",
      "subGroup": "country-flag",
      "order": 3913,
      "sequenceType": "flag",
      "active": true
    },
    {
      "index": 71,
      "row": 4,
      "column": 7,
      "x": 112,
      "y": 64,
      "width": 16,
      "height": 16,
      "key": "flagFrenchSouthernTerritories",
      "name": "flag: French Southern Territories",
      "emoji": "🇹🇫",
      "codePoints": ["1F1F9", "1F1EB"],
      "group": "Flags",
      "subGroup": "country-flag",
      "order": 3914,
      "sequenceType": "flag",
      "active": true
    },
    {
      "index": 72,
      "row": 4,
      "column": 8,
      "x": 128,
      "y": 64,
      "width": 16,
      "height": 16,
      "key": "flagTogo",
      "name": "flag: Togo",
      "emoji": "🇹🇬",
      "codePoints": ["1F1F9", "1F1EC"],
      "group": "Flags",
      "subGroup": "country-flag",
      "order": 3915,
      "sequenceType": "flag",
      "active": true
    },
    {
      "index": 73,
      "row": 4,
      "column": 9,
      "x": 144,
      "y": 64,
      "width": 16,
      "height": 16,
      "key": "flagThailand",
      "name": "flag: Thailand",
      "emoji": "🇹🇭",
      "codePoints": ["1F1F9", "1F1ED"],
      "group": "Flags",
      "subGroup": "country-flag",
      "order": 3916,
      "sequenceType": "flag",
      "active": true
    },
    {
      "index": 74,
      "row": 4,
      "column": 10,
      "x": 160,
      "y": 64,
      "width": 16,
      "height": 16,
      "key": "flagTajikistan",
      "name": "flag: Tajikistan",
      "emoji": "🇹🇯",
      "codePoints": ["1F1F9", "1F1EF"],
      "group": "Flags",
      "subGroup": "country-flag",
      "order": 3917,
      "sequenceType": "flag",
      "active": true
    },
    {
      "index": 75,
      "row": 4,
      "column": 11,
      "x": 176,
      "y": 64,
      "width": 16,
      "height": 16,
      "key": "flagTokelau",
      "name": "flag: Tokelau",
      "emoji": "🇹🇰",
      "codePoints": ["1F1F9", "1F1F0"],
      "group": "Flags",
      "subGroup": "country-flag",
      "order": 3918,
      "sequenceType": "flag",
      "active": true
    },
    {
      "index": 76,
      "row": 4,
      "column": 12,
      "x": 192,
      "y": 64,
      "width": 16,
      "height": 16,
      "key": "flagTimorLeste",
      "name": "flag: Timor-Leste",
      "emoji": "🇹🇱",
      "codePoints": ["1F1F9", "1F1F1"],
      "group": "Flags",
      "subGroup": "country-flag",
      "order": 3919,
      "sequenceType": "flag",
      "active": true
    },
    {
      "index": 77,
      "row": 4,
      "column": 13,
      "x": 208,
      "y": 64,
      "width": 16,
      "height": 16,
      "key": "flagTurkmenistan",
      "name": "flag: Turkmenistan",
      "emoji": "🇹🇲",
      "codePoints": ["1F1F9", "1F1F2"],
      "group": "Flags",
      "subGroup": "country-flag",
      "order": 3920,
      "sequenceType": "flag",
      "active": true
    },
    {
      "index": 78,
      "row": 4,
      "column": 14,
      "x": 224,
      "y": 64,
      "width": 16,
      "height": 16,
      "key": "flagTunisia",
      "name": "flag: Tunisia",
      "emoji": "🇹🇳",
      "codePoints": ["1F1F9", "1F1F3"],
      "group": "Flags",
      "subGroup": "country-flag",
      "order": 3921,
      "sequenceType": "flag",
      "active": true
    },
    {
      "index": 79,
      "row": 4,
      "column": 15,
      "x": 240,
      "y": 64,
      "width": 16,
      "height": 16,
      "key": "flagTonga",
      "name": "flag: Tonga",
      "emoji": "🇹🇴",
      "codePoints": ["1F1F9", "1F1F4"],
      "group": "Flags",
      "subGroup": "country-flag",
      "order": 3922,
      "sequenceType": "flag",
      "active": true
    },
    {
      "index": 80,
      "row": 5,
      "column": 0,
      "x": 0,
      "y": 80,
      "width": 16,
      "height": 16,
      "key": "flagTurkiye",
      "name": "flag: Türkiye",
      "emoji": "🇹🇷",
      "codePoints": ["1F1F9", "1F1F7"],
      "group": "Flags",
      "subGroup": "country-flag",
      "order": 3923,
      "sequenceType": "flag",
      "active": true
    },
    {
      "index": 81,
      "row": 5,
      "column": 1,
      "x": 16,
      "y": 80,
      "width": 16,
      "height": 16,
      "key": "flagTrinidadAndTobago",
      "name": "flag: Trinidad & Tobago",
      "emoji": "🇹🇹",
      "codePoints": ["1F1F9", "1F1F9"],
      "group": "Flags",
      "subGroup": "country-flag",
      "order": 3924,
      "sequenceType": "flag",
      "active": true
    },
    {
      "index": 82,
      "row": 5,
      "column": 2,
      "x": 32,
      "y": 80,
      "width": 16,
      "height": 16,
      "key": "flagTuvalu",
      "name": "flag: Tuvalu",
      "emoji": "🇹🇻",
      "codePoints": ["1F1F9", "1F1FB"],
      "group": "Flags",
      "subGroup": "country-flag",
      "order": 3925,
      "sequenceType": "flag",
      "active": true
    },
    {
      "index": 83,
      "row": 5,
      "column": 3,
      "x": 48,
      "y": 80,
      "width": 16,
      "height": 16,
      "key": "flagTaiwan",
      "name": "flag: Taiwan",
      "emoji": "🇹🇼",
      "codePoints": ["1F1F9", "1F1FC"],
      "group": "Flags",
      "subGroup": "country-flag",
      "order": 3926,
      "sequenceType": "flag",
      "active": true
    },
    {
      "index": 84,
      "row": 5,
      "column": 4,
      "x": 64,
      "y": 80,
      "width": 16,
      "height": 16,
      "key": "flagTanzania",
      "name": "flag: Tanzania",
      "emoji": "🇹🇿",
      "codePoints": ["1F1F9", "1F1FF"],
      "group": "Flags",
      "subGroup": "country-flag",
      "order": 3927,
      "sequenceType": "flag",
      "active": true
    },
    {
      "index": 85,
      "row": 5,
      "column": 5,
      "x": 80,
      "y": 80,
      "width": 16,
      "height": 16,
      "key": "flagUkraine",
      "name": "flag: Ukraine",
      "emoji": "🇺🇦",
      "codePoints": ["1F1FA", "1F1E6"],
      "group": "Flags",
      "subGroup": "country-flag",
      "order": 3928,
      "sequenceType": "flag",
      "active": true
    },
    {
      "index": 86,
      "row": 5,
      "column": 6,
      "x": 96,
      "y": 80,
      "width": 16,
      "height": 16,
      "key": "flagUganda",
      "name": "flag: Uganda",
      "emoji": "🇺🇬",
      "codePoints": ["1F1FA", "1F1EC"],
      "group": "Flags",
      "subGroup": "country-flag",
      "order": 3929,
      "sequenceType": "flag",
      "active": true
    },
    {
      "index": 87,
      "row": 5,
      "column": 7,
      "x": 112,
      "y": 80,
      "width": 16,
      "height": 16,
      "key": "flagUSOutlyingIslands",
      "name": "flag: U.S. Outlying Islands",
      "emoji": "🇺🇲",
      "codePoints": ["1F1FA", "1F1F2"],
      "group": "Flags",
      "subGroup": "country-flag",
      "order": 3930,
      "sequenceType": "flag",
      "active": true
    },
    {
      "index": 88,
      "row": 5,
      "column": 8,
      "x": 128,
      "y": 80,
      "width": 16,
      "height": 16,
      "key": "flagUnitedNations",
      "name": "flag: United Nations",
      "emoji": "🇺🇳",
      "codePoints": ["1F1FA", "1F1F3"],
      "group": "Flags",
      "subGroup": "country-flag",
      "order": 3931,
      "sequenceType": "flag",
      "active": true
    },
    {
      "index": 89,
      "row": 5,
      "column": 9,
      "x": 144,
      "y": 80,
      "width": 16,
      "height": 16,
      "key": "flagUnitedStates",
      "name": "flag: United States",
      "emoji": "🇺🇸",
      "codePoints": ["1F1FA", "1F1F8"],
      "group": "Flags",
      "subGroup": "country-flag",
      "order": 3932,
      "sequenceType": "flag",
      "active": true
    },
    {
      "index": 90,
      "row": 5,
      "column": 10,
      "x": 160,
      "y": 80,
      "width": 16,
      "height": 16,
      "key": "flagUruguay",
      "name": "flag: Uruguay",
      "emoji": "🇺🇾",
      "codePoints": ["1F1FA", "1F1FE"],
      "group": "Flags",
      "subGroup": "country-flag",
      "order": 3933,
      "sequenceType": "flag",
      "active": true
    },
    {
      "index": 91,
      "row": 5,
      "column": 11,
      "x": 176,
      "y": 80,
      "width": 16,
      "height": 16,
      "key": "flagUzbekistan",
      "name": "flag: Uzbekistan",
      "emoji": "🇺🇿",
      "codePoints": ["1F1FA", "1F1FF"],
      "group": "Flags",
      "subGroup": "country-flag",
      "order": 3934,
      "sequenceType": "flag",
      "active": true
    },
    {
      "index": 92,
      "row": 5,
      "column": 12,
      "x": 192,
      "y": 80,
      "width": 16,
      "height": 16,
      "key": "flagVaticanCity",
      "name": "flag: Vatican City",
      "emoji": "🇻🇦",
      "codePoints": ["1F1FB", "1F1E6"],
      "group": "Flags",
      "subGroup": "country-flag",
      "order": 3935,
      "sequenceType": "flag",
      "active": true
    },
    {
      "index": 93,
      "row": 5,
      "column": 13,
      "x": 208,
      "y": 80,
      "width": 16,
      "height": 16,
      "key": "flagStVincentAndGrenadines",
      "name": "flag: St. Vincent & Grenadines",
      "emoji": "🇻🇨",
      "codePoints": ["1F1FB", "1F1E8"],
      "group": "Flags",
      "subGroup": "country-flag",
      "order": 3936,
      "sequenceType": "flag",
      "active": true
    },
    {
      "index": 94,
      "row": 5,
      "column": 14,
      "x": 224,
      "y": 80,
      "width": 16,
      "height": 16,
      "key": "flagVenezuela",
      "name": "flag: Venezuela",
      "emoji": "🇻🇪",
      "codePoints": ["1F1FB", "1F1EA"],
      "group": "Flags",
      "subGroup": "country-flag",
      "order": 3937,
      "sequenceType": "flag",
      "active": true
    },
    {
      "index": 95,
      "row": 5,
      "column": 15,
      "x": 240,
      "y": 80,
      "width": 16,
      "height": 16,
      "key": "flagBritishVirginIslands",
      "name": "flag: British Virgin Islands",
      "emoji": "🇻🇬",
      "codePoints": ["1F1FB", "1F1EC"],
      "group": "Flags",
      "subGroup": "country-flag",
      "order": 3938,
      "sequenceType": "flag",
      "active": true
    },
    {
      "index": 96,
      "row": 6,
      "column": 0,
      "x": 0,
      "y": 96,
      "width": 16,
      "height": 16,
      "key": "flagUSVirginIslands",
      "name": "flag: U.S. Virgin Islands",
      "emoji": "🇻🇮",
      "codePoints": ["1F1FB", "1F1EE"],
      "group": "Flags",
      "subGroup": "country-flag",
      "order": 3939,
      "sequenceType": "flag",
      "active": true
    },
    {
      "index": 97,
      "row": 6,
      "column": 1,
      "x": 16,
      "y": 96,
      "width": 16,
      "height": 16,
      "key": "flagVietnam",
      "name": "flag: Vietnam",
      "emoji": "🇻🇳",
      "codePoints": ["1F1FB", "1F1F3"],
      "group": "Flags",
      "subGroup": "country-flag",
      "order": 3940,
      "sequenceType": "flag",
      "active": true
    },
    {
      "index": 98,
      "row": 6,
      "column": 2,
      "x": 32,
      "y": 96,
      "width": 16,
      "height": 16,
      "key": "flagVanuatu",
      "name": "flag: Vanuatu",
      "emoji": "🇻🇺",
      "codePoints": ["1F1FB", "1F1FA"],
      "group": "Flags",
      "subGroup": "country-flag",
      "order": 3941,
      "sequenceType": "flag",
      "active": true
    },
    {
      "index": 99,
      "row": 6,
      "column": 3,
      "x": 48,
      "y": 96,
      "width": 16,
      "height": 16,
      "key": "flagWallisAndFutuna",
      "name": "flag: Wallis & Futuna",
      "emoji": "🇼🇫",
      "codePoints": ["1F1FC", "1F1EB"],
      "group": "Flags",
      "subGroup": "country-flag",
      "order": 3942,
      "sequenceType": "flag",
      "active": true
    },
    {
      "index": 100,
      "row": 6,
      "column": 4,
      "x": 64,
      "y": 96,
      "width": 16,
      "height": 16,
      "key": "flagSamoa",
      "name": "flag: Samoa",
      "emoji": "🇼🇸",
      "codePoints": ["1F1FC", "1F1F8"],
      "group": "Flags",
      "subGroup": "country-flag",
      "order": 3943,
      "sequenceType": "flag",
      "active": true
    },
    {
      "index": 101,
      "row": 6,
      "column": 5,
      "x": 80,
      "y": 96,
      "width": 16,
      "height": 16,
      "key": "flagKosovo",
      "name": "flag: Kosovo",
      "emoji": "🇽🇰",
      "codePoints": ["1F1FD", "1F1F0"],
      "group": "Flags",
      "subGroup": "country-flag",
      "order": 3944,
      "sequenceType": "flag",
      "active": true
    },
    {
      "index": 102,
      "row": 6,
      "column": 6,
      "x": 96,
      "y": 96,
      "width": 16,
      "height": 16,
      "key": "flagYemen",
      "name": "flag: Yemen",
      "emoji": "🇾🇪",
      "codePoints": ["1F1FE", "1F1EA"],
      "group": "Flags",
      "subGroup": "country-flag",
      "order": 3945,
      "sequenceType": "flag",
      "active": true
    },
    {
      "index": 103,
      "row": 6,
      "column": 7,
      "x": 112,
      "y": 96,
      "width": 16,
      "height": 16,
      "key": "flagMayotte",
      "name": "flag: Mayotte",
      "emoji": "🇾🇹",
      "codePoints": ["1F1FE", "1F1F9"],
      "group": "Flags",
      "subGroup": "country-flag",
      "order": 3946,
      "sequenceType": "flag",
      "active": true
    },
    {
      "index": 104,
      "row": 6,
      "column": 8,
      "x": 128,
      "y": 96,
      "width": 16,
      "height": 16,
      "key": "flagSouthAfrica",
      "name": "flag: South Africa",
      "emoji": "🇿🇦",
      "codePoints": ["1F1FF", "1F1E6"],
      "group": "Flags",
      "subGroup": "country-flag",
      "order": 3947,
      "sequenceType": "flag",
      "active": true
    },
    {
      "index": 105,
      "row": 6,
      "column": 9,
      "x": 144,
      "y": 96,
      "width": 16,
      "height": 16,
      "key": "flagZambia",
      "name": "flag: Zambia",
      "emoji": "🇿🇲",
      "codePoints": ["1F1FF", "1F1F2"],
      "group": "Flags",
      "subGroup": "country-flag",
      "order": 3948,
      "sequenceType": "flag",
      "active": true
    },
    {
      "index": 106,
      "row": 6,
      "column": 10,
      "x": 160,
      "y": 96,
      "width": 16,
      "height": 16,
      "key": "flagZimbabwe",
      "name": "flag: Zimbabwe",
      "emoji": "🇿🇼",
      "codePoints": ["1F1FF", "1F1FC"],
      "group": "Flags",
      "subGroup": "country-flag",
      "order": 3949,
      "sequenceType": "flag",
      "active": true
    },
    {
      "index": 107,
      "row": 6,
      "column": 11,
      "x": 176,
      "y": 96,
      "width": 16,
      "height": 16,
      "key": "flagEngland",
      "name": "flag: England",
      "emoji": "🏴󠁧󠁢󠁥󠁮󠁧󠁿",
      "codePoints": [
        "1F3F4",
        "E0067",
        "E0062",
        "E0065",
        "E006E",
        "E0067",
        "E007F"
      ],
      "group": "Flags",
      "subGroup": "subdivision-flag",
      "order": 3950,
      "sequenceType": "tag",
      "active": true
    },
    {
      "index": 108,
      "row": 6,
      "column": 12,
      "x": 192,
      "y": 96,
      "width": 16,
      "height": 16,
      "key": "flagScotland",
      "name": "flag: Scotland",
      "emoji": "🏴󠁧󠁢󠁳󠁣󠁴󠁿",
      "codePoints": [
        "1F3F4",
        "E0067",
        "E0062",
        "E0073",
        "E0063",
        "E0074",
        "E007F"
      ],
      "group": "Flags",
      "subGroup": "subdivision-flag",
      "order": 3951,
      "sequenceType": "tag",
      "active": true
    },
    {
      "index": 109,
      "row": 6,
      "column": 13,
      "x": 208,
      "y": 96,
      "width": 16,
      "height": 16,
      "key": "flagWales",
      "name": "flag: Wales",
      "emoji": "🏴󠁧󠁢󠁷󠁬󠁳󠁿",
      "codePoints": [
        "1F3F4",
        "E0067",
        "E0062",
        "E0077",
        "E006C",
        "E0073",
        "E007F"
      ],
      "group": "Flags",
      "subGroup": "subdivision-flag",
      "order": 3952,
      "sequenceType": "tag",
      "active": true
    }
  ]
}
