{
  "schemaVersion": 3,
  "id": "modifiers/skin-tone/people-and-body/person-role-01",
  "image": "modifiers/skin-tone/people-and-body/person-role-01.png",
  "modifierType": "skin-tone",
  "group": "People & Body",
  "subGroup": "person-role",
  "part": 1,
  "partCount": 4,
  "rows": 8,
  "imageWidth": 272,
  "imageHeight": 192,
  "entries": [
    {
      "index": 0,
      "row": 0,
      "column": 0,
      "x": 10,
      "y": 42,
      "width": 12,
      "height": 12,
      "key": "healthWorkerLightSkinTone",
      "name": "health worker: light skin tone",
      "emoji": "рџ§‘рџЏ»вЂЌвљ•пёЏ",
      "codePoints": ["1F9D1", "1F3FB", "200D", "2695", "FE0F"],
      "order": 846,
      "sequenceType": "zwj",
      "active": true
    },
    {
      "index": 1,
      "row": 0,
      "column": 1,
      "x": 26,
      "y": 42,
      "width": 12,
      "height": 12,
      "key": "healthWorkerMediumLightSkinTone",
      "name": "health worker: medium-light skin tone",
      "emoji": "рџ§‘рџЏјвЂЌвљ•пёЏ",
      "codePoints": ["1F9D1", "1F3FC", "200D", "2695", "FE0F"],
      "order": 847,
      "sequenceType": "zwj",
      "active": true
    },
    {
      "index": 2,
      "row": 0,
      "column": 2,
      "x": 42,
      "y": 42,
      "width": 12,
      "height": 12,
      "key": "healthWorkerMediumSkinTone",
      "name": "health worker: medium skin tone",
      "emoji": "рџ§‘рџЏЅвЂЌвљ•пёЏ",
      "codePoints": ["1F9D1", "1F3FD", "200D", "2695", "FE0F"],
      "order": 848,
      "sequenceType": "zwj",
      "active": true
    },
    {
      "index": 3,
      "row": 0,
      "column": 3,
      "x": 58,
      "y": 42,
      "width": 12,
      "height": 12,
      "key": "healthWorkerMediumDarkSkinTone",
      "name": "health worker: medium-dark skin tone",
      "emoji": "рџ§‘рџЏѕвЂЌвљ•пёЏ",
      "codePoints": ["1F9D1", "1F3FE", "200D", "2695", "FE0F"],
      "order": 849,
      "sequenceType": "zwj",
      "active": true
    },
    {
      "index": 4,
      "row": 0,
      "column": 4,
      "x": 74,
      "y": 42,
      "width": 12,
      "height": 12,
      "key": "healthWorkerDarkSkinTone",
      "name": "health worker: dark skin tone",
      "emoji": "рџ§‘рџЏївЂЌвљ•пёЏ",
      "codePoints": ["1F9D1", "1F3FF", "200D", "2695", "FE0F"],
      "order": 850,
      "sequenceType": "zwj",
      "active": true
    },
    {
      "index": 5,
      "row": 0,
      "column": 5,
      "x": 90,
      "y": 42,
      "width": 12,
      "height": 12,
      "key": "manHealthWorkerLightSkinTone",
      "name": "man health worker: light skin tone",
      "emoji": "рџ‘ЁрџЏ»вЂЌвљ•пёЏ",
      "codePoints": ["1F468", "1F3FB", "200D", "2695", "FE0F"],
      "order": 852,
      "sequenceType": "zwj",
      "active": true
    },
    {
      "index": 6,
      "row": 0,
      "column": 6,
      "x": 106,
      "y": 42,
      "width": 12,
      "height": 12,
      "key": "manHealthWorkerMediumLightSkinTone",
      "name": "man health worker: medium-light skin tone",
      "emoji": "рџ‘ЁрџЏјвЂЌвљ•пёЏ",
      "codePoints": ["1F468", "1F3FC", "200D", "2695", "FE0F"],
      "order": 853,
      "sequenceType": "zwj",
      "active": true
    },
    {
      "index": 7,
      "row": 0,
      "column": 7,
      "x": 122,
      "y": 42,
      "width": 12,
      "height": 12,
      "key": "manHealthWorkerMediumSkinTone",
      "name": "man health worker: medium skin tone",
      "emoji": "рџ‘ЁрџЏЅвЂЌвљ•пёЏ",
      "codePoints": ["1F468", "1F3FD", "200D", "2695", "FE0F"],
      "order": 854,
      "sequenceType": "zwj",
      "active": true
    },
    {
      "index": 8,
      "row": 0,
      "column": 8,
      "x": 138,
      "y": 42,
      "width": 12,
      "height": 12,
      "key": "manHealthWorkerMediumDarkSkinTone",
      "name": "man health worker: medium-dark skin tone",
      "emoji": "рџ‘ЁрџЏѕвЂЌвљ•пёЏ",
      "codePoints": ["1F468", "1F3FE", "200D", "2695", "FE0F"],
      "order": 855,
      "sequenceType": "zwj",
      "active": true
    },
    {
      "index": 9,
      "row": 0,
      "column": 9,
      "x": 154,
      "y": 42,
      "width": 12,
      "height": 12,
      "key": "manHealthWorkerDarkSkinTone",
      "name": "man health worker: dark skin tone",
      "emoji": "рџ‘ЁрџЏївЂЌвљ•пёЏ",
      "codePoints": ["1F468", "1F3FF", "200D", "2695", "FE0F"],
      "order": 856,
      "sequenceType": "zwj",
      "active": true
    },
    {
      "index": 10,
      "row": 0,
      "column": 10,
      "x": 170,
      "y": 42,
      "width": 12,
      "height": 12,
      "key": "womanHealthWorkerLightSkinTone",
      "name": "woman health worker: light skin tone",
      "emoji": "рџ‘©рџЏ»вЂЌвљ•пёЏ",
      "codePoints": ["1F469", "1F3FB", "200D", "2695", "FE0F"],
      "order": 858,
      "sequenceType": "zwj",
      "active": true
    },
    {
      "index": 11,
      "row": 0,
      "column": 11,
      "x": 186,
      "y": 42,
      "width": 12,
      "height": 12,
      "key": "womanHealthWorkerMediumLightSkinTone",
      "name": "woman health worker: medium-light skin tone",
      "emoji": "рџ‘©рџЏјвЂЌвљ•пёЏ",
      "codePoints": ["1F469", "1F3FC", "200D", "2695", "FE0F"],
      "order": 859,
      "sequenceType": "zwj",
      "active": true
    },
    {
      "index": 12,
      "row": 0,
      "column": 12,
      "x": 202,
      "y": 42,
      "width": 12,
      "height": 12,
      "key": "womanHealthWorkerMediumSkinTone",
      "name": "woman health worker: medium skin tone",
      "emoji": "рџ‘©рџЏЅвЂЌвљ•пёЏ",
      "codePoints": ["1F469", "1F3FD", "200D", "2695", "FE0F"],
      "order": 860,
      "sequenceType": "zwj",
      "active": true
    },
    {
      "index": 13,
      "row": 0,
      "column": 13,
      "x": 218,
      "y": 42,
      "width": 12,
      "height": 12,
      "key": "womanHealthWorkerMediumDarkSkinTone",
      "name": "woman health worker: medium-dark skin tone",
      "emoji": "рџ‘©рџЏѕвЂЌвљ•пёЏ",
      "codePoints": ["1F469", "1F3FE", "200D", "2695", "FE0F"],
      "order": 861,
      "sequenceType": "zwj",
      "active": true
    },
    {
      "index": 14,
      "row": 0,
      "column": 14,
      "x": 234,
      "y": 42,
      "width": 12,
      "height": 12,
      "key": "womanHealthWorkerDarkSkinTone",
      "name": "woman health worker: dark skin tone",
      "emoji": "рџ‘©рџЏївЂЌвљ•пёЏ",
      "codePoints": ["1F469", "1F3FF", "200D", "2695", "FE0F"],
      "order": 862,
      "sequenceType": "zwj",
      "active": true
    },
    {
      "index": 15,
      "row": 0,
      "column": 15,
      "x": 250,
      "y": 42,
      "width": 12,
      "height": 12,
      "key": "studentLightSkinTone",
      "name": "student: light skin tone",
      "emoji": "рџ§‘рџЏ»вЂЌрџЋ“",
      "codePoints": ["1F9D1", "1F3FB", "200D", "1F393"],
      "order": 864,
      "sequenceType": "zwj",
      "active": true
    },
    {
      "index": 16,
      "row": 1,
      "column": 0,
      "x": 10,
      "y": 58,
      "width": 12,
      "height": 12,
      "key": "studentMediumLightSkinTone",
      "name": "student: medium-light skin tone",
      "emoji": "рџ§‘рџЏјвЂЌрџЋ“",
      "codePoints": ["1F9D1", "1F3FC", "200D", "1F393"],
      "order": 865,
      "sequenceType": "zwj",
      "active": true
    },
    {
      "index": 17,
      "row": 1,
      "column": 1,
      "x": 26,
      "y": 58,
      "width": 12,
      "height": 12,
      "key": "studentMediumSkinTone",
      "name": "student: medium skin tone",
      "emoji": "рџ§‘рџЏЅвЂЌрџЋ“",
      "codePoints": ["1F9D1", "1F3FD", "200D", "1F393"],
      "order": 866,
      "sequenceType": "zwj",
      "active": true
    },
    {
      "index": 18,
      "row": 1,
      "column": 2,
      "x": 42,
      "y": 58,
      "width": 12,
      "height": 12,
      "key": "studentMediumDarkSkinTone",
      "name": "student: medium-dark skin tone",
      "emoji": "рџ§‘рџЏѕвЂЌрџЋ“",
      "codePoints": ["1F9D1", "1F3FE", "200D", "1F393"],
      "order": 867,
      "sequenceType": "zwj",
      "active": true
    },
    {
      "index": 19,
      "row": 1,
      "column": 3,
      "x": 58,
      "y": 58,
      "width": 12,
      "height": 12,
      "key": "studentDarkSkinTone",
      "name": "student: dark skin tone",
      "emoji": "рџ§‘рџЏївЂЌрџЋ“",
      "codePoints": ["1F9D1", "1F3FF", "200D", "1F393"],
      "order": 868,
      "sequenceType": "zwj",
      "active": true
    },
    {
      "index": 20,
      "row": 1,
      "column": 4,
      "x": 74,
      "y": 58,
      "width": 12,
      "height": 12,
      "key": "manStudentLightSkinTone",
      "name": "man student: light skin tone",
      "emoji": "рџ‘ЁрџЏ»вЂЌрџЋ“",
      "codePoints": ["1F468", "1F3FB", "200D", "1F393"],
      "order": 870,
      "sequenceType": "zwj",
      "active": true
    },
    {
      "index": 21,
      "row": 1,
      "column": 5,
      "x": 90,
      "y": 58,
      "width": 12,
      "height": 12,
      "key": "manStudentMediumLightSkinTone",
      "name": "man student: medium-light skin tone",
      "emoji": "рџ‘ЁрџЏјвЂЌрџЋ“",
      "codePoints": ["1F468", "1F3FC", "200D", "1F393"],
      "order": 871,
      "sequenceType": "zwj",
      "active": true
    },
    {
      "index": 22,
      "row": 1,
      "column": 6,
      "x": 106,
      "y": 58,
      "width": 12,
      "height": 12,
      "key": "manStudentMediumSkinTone",
      "name": "man student: medium skin tone",
      "emoji": "рџ‘ЁрџЏЅвЂЌрџЋ“",
      "codePoints": ["1F468", "1F3FD", "200D", "1F393"],
      "order": 872,
      "sequenceType": "zwj",
      "active": true
    },
    {
      "index": 23,
      "row": 1,
      "column": 7,
      "x": 122,
      "y": 58,
      "width": 12,
      "height": 12,
      "key": "manStudentMediumDarkSkinTone",
      "name": "man student: medium-dark skin tone",
      "emoji": "рџ‘ЁрџЏѕвЂЌрџЋ“",
      "codePoints": ["1F468", "1F3FE", "200D", "1F393"],
      "order": 873,
      "sequenceType": "zwj",
      "active": true
    },
    {
      "index": 24,
      "row": 1,
      "column": 8,
      "x": 138,
      "y": 58,
      "width": 12,
      "height": 12,
      "key": "manStudentDarkSkinTone",
      "name": "man student: dark skin tone",
      "emoji": "рџ‘ЁрџЏївЂЌрџЋ“",
      "codePoints": ["1F468", "1F3FF", "200D", "1F393"],
      "order": 874,
      "sequenceType": "zwj",
      "active": true
    },
    {
      "index": 25,
      "row": 1,
      "column": 9,
      "x": 154,
      "y": 58,
      "width": 12,
      "height": 12,
      "key": "womanStudentLightSkinTone",
      "name": "woman student: light skin tone",
      "emoji": "рџ‘©рџЏ»вЂЌрџЋ“",
      "codePoints": ["1F469", "1F3FB", "200D", "1F393"],
      "order": 876,
      "sequenceType": "zwj",
      "active": true
    },
    {
      "index": 26,
      "row": 1,
      "column": 10,
      "x": 170,
      "y": 58,
      "width": 12,
      "height": 12,
      "key": "womanStudentMediumLightSkinTone",
      "name": "woman student: medium-light skin tone",
      "emoji": "рџ‘©рџЏјвЂЌрџЋ“",
      "codePoints": ["1F469", "1F3FC", "200D", "1F393"],
      "order": 877,
      "sequenceType": "zwj",
      "active": true
    },
    {
      "index": 27,
      "row": 1,
      "column": 11,
      "x": 186,
      "y": 58,
      "width": 12,
      "height": 12,
      "key": "womanStudentMediumSkinTone",
      "name": "woman student: medium skin tone",
      "emoji": "рџ‘©рџЏЅвЂЌрџЋ“",
      "codePoints": ["1F469", "1F3FD", "200D", "1F393"],
      "order": 878,
      "sequenceType": "zwj",
      "active": true
    },
    {
      "index": 28,
      "row": 1,
      "column": 12,
      "x": 202,
      "y": 58,
      "width": 12,
      "height": 12,
      "key": "womanStudentMediumDarkSkinTone",
      "name": "woman student: medium-dark skin tone",
      "emoji": "рџ‘©рџЏѕвЂЌрџЋ“",
      "codePoints": ["1F469", "1F3FE", "200D", "1F393"],
      "order": 879,
      "sequenceType": "zwj",
      "active": true
    },
    {
      "index": 29,
      "row": 1,
      "column": 13,
      "x": 218,
      "y": 58,
      "width": 12,
      "height": 12,
      "key": "womanStudentDarkSkinTone",
      "name": "woman student: dark skin tone",
      "emoji": "рџ‘©рџЏївЂЌрџЋ“",
      "codePoints": ["1F469", "1F3FF", "200D", "1F393"],
      "order": 880,
      "sequenceType": "zwj",
      "active": true
    },
    {
      "index": 30,
      "row": 1,
      "column": 14,
      "x": 234,
      "y": 58,
      "width": 12,
      "height": 12,
      "key": "teacherLightSkinTone",
      "name": "teacher: light skin tone",
      "emoji": "рџ§‘рџЏ»вЂЌрџЏ«",
      "codePoints": ["1F9D1", "1F3FB", "200D", "1F3EB"],
      "order": 882,
      "sequenceType": "zwj",
      "active": true
    },
    {
      "index": 31,
      "row": 1,
      "column": 15,
      "x": 250,
      "y": 58,
      "width": 12,
      "height": 12,
      "key": "teacherMediumLightSkinTone",
      "name": "teacher: medium-light skin tone",
      "emoji": "рџ§‘рџЏјвЂЌрџЏ«",
      "codePoints": ["1F9D1", "1F3FC", "200D", "1F3EB"],
      "order": 883,
      "sequenceType": "zwj",
      "active": true
    },
    {
      "index": 32,
      "row": 2,
      "column": 0,
      "x": 10,
      "y": 74,
      "width": 12,
      "height": 12,
      "key": "teacherMediumSkinTone",
      "name": "teacher: medium skin tone",
      "emoji": "рџ§‘рџЏЅвЂЌрџЏ«",
      "codePoints": ["1F9D1", "1F3FD", "200D", "1F3EB"],
      "order": 884,
      "sequenceType": "zwj",
      "active": true
    },
    {
      "index": 33,
      "row": 2,
      "column": 1,
      "x": 26,
      "y": 74,
      "width": 12,
      "height": 12,
      "key": "teacherMediumDarkSkinTone",
      "name": "teacher: medium-dark skin tone",
      "emoji": "рџ§‘рџЏѕвЂЌрџЏ«",
      "codePoints": ["1F9D1", "1F3FE", "200D", "1F3EB"],
      "order": 885,
      "sequenceType": "zwj",
      "active": true
    },
    {
      "index": 34,
      "row": 2,
      "column": 2,
      "x": 42,
      "y": 74,
      "width": 12,
      "height": 12,
      "key": "teacherDarkSkinTone",
      "name": "teacher: dark skin tone",
      "emoji": "рџ§‘рџЏївЂЌрџЏ«",
      "codePoints": ["1F9D1", "1F3FF", "200D", "1F3EB"],
      "order": 886,
      "sequenceType": "zwj",
      "active": true
    },
    {
      "index": 35,
      "row": 2,
      "column": 3,
      "x": 58,
      "y": 74,
      "width": 12,
      "height": 12,
      "key": "manTeacherLightSkinTone",
      "name": "man teacher: light skin tone",
      "emoji": "рџ‘ЁрџЏ»вЂЌрџЏ«",
      "codePoints": ["1F468", "1F3FB", "200D", "1F3EB"],
      "order": 888,
      "sequenceType": "zwj",
      "active": true
    },
    {
      "index": 36,
      "row": 2,
      "column": 4,
      "x": 74,
      "y": 74,
      "width": 12,
      "height": 12,
      "key": "manTeacherMediumLightSkinTone",
      "name": "man teacher: medium-light skin tone",
      "emoji": "рџ‘ЁрџЏјвЂЌрџЏ«",
      "codePoints": ["1F468", "1F3FC", "200D", "1F3EB"],
      "order": 889,
      "sequenceType": "zwj",
      "active": true
    },
    {
      "index": 37,
      "row": 2,
      "column": 5,
      "x": 90,
      "y": 74,
      "width": 12,
      "height": 12,
      "key": "manTeacherMediumSkinTone",
      "name": "man teacher: medium skin tone",
      "emoji": "рџ‘ЁрџЏЅвЂЌрџЏ«",
      "codePoints": ["1F468", "1F3FD", "200D", "1F3EB"],
      "order": 890,
      "sequenceType": "zwj",
      "active": true
    },
    {
      "index": 38,
      "row": 2,
      "column": 6,
      "x": 106,
      "y": 74,
      "width": 12,
      "height": 12,
      "key": "manTeacherMediumDarkSkinTone",
      "name": "man teacher: medium-dark skin tone",
      "emoji": "рџ‘ЁрџЏѕвЂЌрџЏ«",
      "codePoints": ["1F468", "1F3FE", "200D", "1F3EB"],
      "order": 891,
      "sequenceType": "zwj",
      "active": true
    },
    {
      "index": 39,
      "row": 2,
      "column": 7,
      "x": 122,
      "y": 74,
      "width": 12,
      "height": 12,
      "key": "manTeacherDarkSkinTone",
      "name": "man teacher: dark skin tone",
      "emoji": "рџ‘ЁрџЏївЂЌрџЏ«",
      "codePoints": ["1F468", "1F3FF", "200D", "1F3EB"],
      "order": 892,
      "sequenceType": "zwj",
      "active": true
    },
    {
      "index": 40,
      "row": 2,
      "column": 8,
      "x": 138,
      "y": 74,
      "width": 12,
      "height": 12,
      "key": "womanTeacherLightSkinTone",
      "name": "woman teacher: light skin tone",
      "emoji": "рџ‘©рџЏ»вЂЌрџЏ«",
      "codePoints": ["1F469", "1F3FB", "200D", "1F3EB"],
      "order": 894,
      "sequenceType": "zwj",
      "active": true
    },
    {
      "index": 41,
      "row": 2,
      "column": 9,
      "x": 154,
      "y": 74,
      "width": 12,
      "height": 12,
      "key": "womanTeacherMediumLightSkinTone",
      "name": "woman teacher: medium-light skin tone",
      "emoji": "рџ‘©рџЏјвЂЌрџЏ«",
      "codePoints": ["1F469", "1F3FC", "200D", "1F3EB"],
      "order": 895,
      "sequenceType": "zwj",
      "active": true
    },
    {
      "index": 42,
      "row": 2,
      "column": 10,
      "x": 170,
      "y": 74,
      "width": 12,
      "height": 12,
      "key": "womanTeacherMediumSkinTone",
      "name": "woman teacher: medium skin tone",
      "emoji": "рџ‘©рџЏЅвЂЌрџЏ«",
      "codePoints": ["1F469", "1F3FD", "200D", "1F3EB"],
      "order": 896,
      "sequenceType": "zwj",
      "active": true
    },
    {
      "index": 43,
      "row": 2,
      "column": 11,
      "x": 186,
      "y": 74,
      "width": 12,
      "height": 12,
      "key": "womanTeacherMediumDarkSkinTone",
      "name": "woman teacher: medium-dark skin tone",
      "emoji": "рџ‘©рџЏѕвЂЌрџЏ«",
      "codePoints": ["1F469", "1F3FE", "200D", "1F3EB"],
      "order": 897,
      "sequenceType": "zwj",
      "active": true
    },
    {
      "index": 44,
      "row": 2,
      "column": 12,
      "x": 202,
      "y": 74,
      "width": 12,
      "height": 12,
      "key": "womanTeacherDarkSkinTone",
      "name": "woman teacher: dark skin tone",
      "emoji": "рџ‘©рџЏївЂЌрџЏ«",
      "codePoints": ["1F469", "1F3FF", "200D", "1F3EB"],
      "order": 898,
      "sequenceType": "zwj",
      "active": true
    },
    {
      "index": 45,
      "row": 2,
      "column": 13,
      "x": 218,
      "y": 74,
      "width": 12,
      "height": 12,
      "key": "judgeLightSkinTone",
      "name": "judge: light skin tone",
      "emoji": "рџ§‘рџЏ»вЂЌвљ–пёЏ",
      "codePoints": ["1F9D1", "1F3FB", "200D", "2696", "FE0F"],
      "order": 900,
      "sequenceType": "zwj",
      "active": true
    },
    {
      "index": 46,
      "row": 2,
      "column": 14,
      "x": 234,
      "y": 74,
      "width": 12,
      "height": 12,
      "key": "judgeMediumLightSkinTone",
      "name": "judge: medium-light skin tone",
      "emoji": "рџ§‘рџЏјвЂЌвљ–пёЏ",
      "codePoints": ["1F9D1", "1F3FC", "200D", "2696", "FE0F"],
      "order": 901,
      "sequenceType": "zwj",
      "active": true
    },
    {
      "index": 47,
      "row": 2,
      "column": 15,
      "x": 250,
      "y": 74,
      "width": 12,
      "height": 12,
      "key": "judgeMediumSkinTone",
      "name": "judge: medium skin tone",
      "emoji": "рџ§‘рџЏЅвЂЌвљ–пёЏ",
      "codePoints": ["1F9D1", "1F3FD", "200D", "2696", "FE0F"],
      "order": 902,
      "sequenceType": "zwj",
      "active": true
    },
    {
      "index": 48,
      "row": 3,
      "column": 0,
      "x": 10,
      "y": 90,
      "width": 12,
      "height": 12,
      "key": "judgeMediumDarkSkinTone",
      "name": "judge: medium-dark skin tone",
      "emoji": "рџ§‘рџЏѕвЂЌвљ–пёЏ",
      "codePoints": ["1F9D1", "1F3FE", "200D", "2696", "FE0F"],
      "order": 903,
      "sequenceType": "zwj",
      "active": true
    },
    {
      "index": 49,
      "row": 3,
      "column": 1,
      "x": 26,
      "y": 90,
      "width": 12,
      "height": 12,
      "key": "judgeDarkSkinTone",
      "name": "judge: dark skin tone",
      "emoji": "рџ§‘рџЏївЂЌвљ–пёЏ",
      "codePoints": ["1F9D1", "1F3FF", "200D", "2696", "FE0F"],
      "order": 904,
      "sequenceType": "zwj",
      "active": true
    },
    {
      "index": 50,
      "row": 3,
      "column": 2,
      "x": 42,
      "y": 90,
      "width": 12,
      "height": 12,
      "key": "manJudgeLightSkinTone",
      "name": "man judge: light skin tone",
      "emoji": "рџ‘ЁрџЏ»вЂЌвљ–пёЏ",
      "codePoints": ["1F468", "1F3FB", "200D", "2696", "FE0F"],
      "order": 906,
      "sequenceType": "zwj",
      "active": true
    },
    {
      "index": 51,
      "row": 3,
      "column": 3,
      "x": 58,
      "y": 90,
      "width": 12,
      "height": 12,
      "key": "manJudgeMediumLightSkinTone",
      "name": "man judge: medium-light skin tone",
      "emoji": "рџ‘ЁрџЏјвЂЌвљ–пёЏ",
      "codePoints": ["1F468", "1F3FC", "200D", "2696", "FE0F"],
      "order": 907,
      "sequenceType": "zwj",
      "active": true
    },
    {
      "index": 52,
      "row": 3,
      "column": 4,
      "x": 74,
      "y": 90,
      "width": 12,
      "height": 12,
      "key": "manJudgeMediumSkinTone",
      "name": "man judge: medium skin tone",
      "emoji": "рџ‘ЁрџЏЅвЂЌвљ–пёЏ",
      "codePoints": ["1F468", "1F3FD", "200D", "2696", "FE0F"],
      "order": 908,
      "sequenceType": "zwj",
      "active": true
    },
    {
      "index": 53,
      "row": 3,
      "column": 5,
      "x": 90,
      "y": 90,
      "width": 12,
      "height": 12,
      "key": "manJudgeMediumDarkSkinTone",
      "name": "man judge: medium-dark skin tone",
      "emoji": "рџ‘ЁрџЏѕвЂЌвљ–пёЏ",
      "codePoints": ["1F468", "1F3FE", "200D", "2696", "FE0F"],
      "order": 909,
      "sequenceType": "zwj",
      "active": true
    },
    {
      "index": 54,
      "row": 3,
      "column": 6,
      "x": 106,
      "y": 90,
      "width": 12,
      "height": 12,
      "key": "manJudgeDarkSkinTone",
      "name": "man judge: dark skin tone",
      "emoji": "рџ‘ЁрџЏївЂЌвљ–пёЏ",
      "codePoints": ["1F468", "1F3FF", "200D", "2696", "FE0F"],
      "order": 910,
      "sequenceType": "zwj",
      "active": true
    },
    {
      "index": 55,
      "row": 3,
      "column": 7,
      "x": 122,
      "y": 90,
      "width": 12,
      "height": 12,
      "key": "womanJudgeLightSkinTone",
      "name": "woman judge: light skin tone",
      "emoji": "рџ‘©рџЏ»вЂЌвљ–пёЏ",
      "codePoints": ["1F469", "1F3FB", "200D", "2696", "FE0F"],
      "order": 912,
      "sequenceType": "zwj",
      "active": true
    },
    {
      "index": 56,
      "row": 3,
      "column": 8,
      "x": 138,
      "y": 90,
      "width": 12,
      "height": 12,
      "key": "womanJudgeMediumLightSkinTone",
      "name": "woman judge: medium-light skin tone",
      "emoji": "рџ‘©рџЏјвЂЌвљ–пёЏ",
      "codePoints": ["1F469", "1F3FC", "200D", "2696", "FE0F"],
      "order": 913,
      "sequenceType": "zwj",
      "active": true
    },
    {
      "index": 57,
      "row": 3,
      "column": 9,
      "x": 154,
      "y": 90,
      "width": 12,
      "height": 12,
      "key": "womanJudgeMediumSkinTone",
      "name": "woman judge: medium skin tone",
      "emoji": "рџ‘©рџЏЅвЂЌвљ–пёЏ",
      "codePoints": ["1F469", "1F3FD", "200D", "2696", "FE0F"],
      "order": 914,
      "sequenceType": "zwj",
      "active": true
    },
    {
      "index": 58,
      "row": 3,
      "column": 10,
      "x": 170,
      "y": 90,
      "width": 12,
      "height": 12,
      "key": "womanJudgeMediumDarkSkinTone",
      "name": "woman judge: medium-dark skin tone",
      "emoji": "рџ‘©рџЏѕвЂЌвљ–пёЏ",
      "codePoints": ["1F469", "1F3FE", "200D", "2696", "FE0F"],
      "order": 915,
      "sequenceType": "zwj",
      "active": true
    },
    {
      "index": 59,
      "row": 3,
      "column": 11,
      "x": 186,
      "y": 90,
      "width": 12,
      "height": 12,
      "key": "womanJudgeDarkSkinTone",
      "name": "woman judge: dark skin tone",
      "emoji": "рџ‘©рџЏївЂЌвљ–пёЏ",
      "codePoints": ["1F469", "1F3FF", "200D", "2696", "FE0F"],
      "order": 916,
      "sequenceType": "zwj",
      "active": true
    },
    {
      "index": 60,
      "row": 3,
      "column": 12,
      "x": 202,
      "y": 90,
      "width": 12,
      "height": 12,
      "key": "farmerLightSkinTone",
      "name": "farmer: light skin tone",
      "emoji": "рџ§‘рџЏ»вЂЌрџЊѕ",
      "codePoints": ["1F9D1", "1F3FB", "200D", "1F33E"],
      "order": 918,
      "sequenceType": "zwj",
      "active": true
    },
    {
      "index": 61,
      "row": 3,
      "column": 13,
      "x": 218,
      "y": 90,
      "width": 12,
      "height": 12,
      "key": "farmerMediumLightSkinTone",
      "name": "farmer: medium-light skin tone",
      "emoji": "рџ§‘рџЏјвЂЌрџЊѕ",
      "codePoints": ["1F9D1", "1F3FC", "200D", "1F33E"],
      "order": 919,
      "sequenceType": "zwj",
      "active": true
    },
    {
      "index": 62,
      "row": 3,
      "column": 14,
      "x": 234,
      "y": 90,
      "width": 12,
      "height": 12,
      "key": "farmerMediumSkinTone",
      "name": "farmer: medium skin tone",
      "emoji": "рџ§‘рџЏЅвЂЌрџЊѕ",
      "codePoints": ["1F9D1", "1F3FD", "200D", "1F33E"],
      "order": 920,
      "sequenceType": "zwj",
      "active": true
    },
    {
      "index": 63,
      "row": 3,
      "column": 15,
      "x": 250,
      "y": 90,
      "width": 12,
      "height": 12,
      "key": "farmerMediumDarkSkinTone",
      "name": "farmer: medium-dark skin tone",
      "emoji": "рџ§‘рџЏѕвЂЌрџЊѕ",
      "codePoints": ["1F9D1", "1F3FE", "200D", "1F33E"],
      "order": 921,
      "sequenceType": "zwj",
      "active": true
    },
    {
      "index": 64,
      "row": 4,
      "column": 0,
      "x": 10,
      "y": 106,
      "width": 12,
      "height": 12,
      "key": "farmerDarkSkinTone",
      "name": "farmer: dark skin tone",
      "emoji": "рџ§‘рџЏївЂЌрџЊѕ",
      "codePoints": ["1F9D1", "1F3FF", "200D", "1F33E"],
      "order": 922,
      "sequenceType": "zwj",
      "active": true
    },
    {
      "index": 65,
      "row": 4,
      "column": 1,
      "x": 26,
      "y": 106,
      "width": 12,
      "height": 12,
      "key": "manFarmerLightSkinTone",
      "name": "man farmer: light skin tone",
      "emoji": "рџ‘ЁрџЏ»вЂЌрџЊѕ",
      "codePoints": ["1F468", "1F3FB", "200D", "1F33E"],
      "order": 924,
      "sequenceType": "zwj",
      "active": true
    },
    {
      "index": 66,
      "row": 4,
      "column": 2,
      "x": 42,
      "y": 106,
      "width": 12,
      "height": 12,
      "key": "manFarmerMediumLightSkinTone",
      "name": "man farmer: medium-light skin tone",
      "emoji": "рџ‘ЁрџЏјвЂЌрџЊѕ",
      "codePoints": ["1F468", "1F3FC", "200D", "1F33E"],
      "order": 925,
      "sequenceType": "zwj",
      "active": true
    },
    {
      "index": 67,
      "row": 4,
      "column": 3,
      "x": 58,
      "y": 106,
      "width": 12,
      "height": 12,
      "key": "manFarmerMediumSkinTone",
      "name": "man farmer: medium skin tone",
      "emoji": "рџ‘ЁрџЏЅвЂЌрџЊѕ",
      "codePoints": ["1F468", "1F3FD", "200D", "1F33E"],
      "order": 926,
      "sequenceType": "zwj",
      "active": true
    },
    {
      "index": 68,
      "row": 4,
      "column": 4,
      "x": 74,
      "y": 106,
      "width": 12,
      "height": 12,
      "key": "manFarmerMediumDarkSkinTone",
      "name": "man farmer: medium-dark skin tone",
      "emoji": "рџ‘ЁрџЏѕвЂЌрџЊѕ",
      "codePoints": ["1F468", "1F3FE", "200D", "1F33E"],
      "order": 927,
      "sequenceType": "zwj",
      "active": true
    },
    {
      "index": 69,
      "row": 4,
      "column": 5,
      "x": 90,
      "y": 106,
      "width": 12,
      "height": 12,
      "key": "manFarmerDarkSkinTone",
      "name": "man farmer: dark skin tone",
      "emoji": "рџ‘ЁрџЏївЂЌрџЊѕ",
      "codePoints": ["1F468", "1F3FF", "200D", "1F33E"],
      "order": 928,
      "sequenceType": "zwj",
      "active": true
    },
    {
      "index": 70,
      "row": 4,
      "column": 6,
      "x": 106,
      "y": 106,
      "width": 12,
      "height": 12,
      "key": "womanFarmerLightSkinTone",
      "name": "woman farmer: light skin tone",
      "emoji": "рџ‘©рџЏ»вЂЌрџЊѕ",
      "codePoints": ["1F469", "1F3FB", "200D", "1F33E"],
      "order": 930,
      "sequenceType": "zwj",
      "active": true
    },
    {
      "index": 71,
      "row": 4,
      "column": 7,
      "x": 122,
      "y": 106,
      "width": 12,
      "height": 12,
      "key": "womanFarmerMediumLightSkinTone",
      "name": "woman farmer: medium-light skin tone",
      "emoji": "рџ‘©рџЏјвЂЌрџЊѕ",
      "codePoints": ["1F469", "1F3FC", "200D", "1F33E"],
      "order": 931,
      "sequenceType": "zwj",
      "active": true
    },
    {
      "index": 72,
      "row": 4,
      "column": 8,
      "x": 138,
      "y": 106,
      "width": 12,
      "height": 12,
      "key": "womanFarmerMediumSkinTone",
      "name": "woman farmer: medium skin tone",
      "emoji": "рџ‘©рџЏЅвЂЌрџЊѕ",
      "codePoints": ["1F469", "1F3FD", "200D", "1F33E"],
      "order": 932,
      "sequenceType": "zwj",
      "active": true
    },
    {
      "index": 73,
      "row": 4,
      "column": 9,
      "x": 154,
      "y": 106,
      "width": 12,
      "height": 12,
      "key": "womanFarmerMediumDarkSkinTone",
      "name": "woman farmer: medium-dark skin tone",
      "emoji": "рџ‘©рџЏѕвЂЌрџЊѕ",
      "codePoints": ["1F469", "1F3FE", "200D", "1F33E"],
      "order": 933,
      "sequenceType": "zwj",
      "active": true
    },
    {
      "index": 74,
      "row": 4,
      "column": 10,
      "x": 170,
      "y": 106,
      "width": 12,
      "height": 12,
      "key": "womanFarmerDarkSkinTone",
      "name": "woman farmer: dark skin tone",
      "emoji": "рџ‘©рџЏївЂЌрџЊѕ",
      "codePoints": ["1F469", "1F3FF", "200D", "1F33E"],
      "order": 934,
      "sequenceType": "zwj",
      "active": true
    },
    {
      "index": 75,
      "row": 4,
      "column": 11,
      "x": 186,
      "y": 106,
      "width": 12,
      "height": 12,
      "key": "cookLightSkinTone",
      "name": "cook: light skin tone",
      "emoji": "рџ§‘рџЏ»вЂЌрџЌі",
      "codePoints": ["1F9D1", "1F3FB", "200D", "1F373"],
      "order": 936,
      "sequenceType": "zwj",
      "active": true
    },
    {
      "index": 76,
      "row": 4,
      "column": 12,
      "x": 202,
      "y": 106,
      "width": 12,
      "height": 12,
      "key": "cookMediumLightSkinTone",
      "name": "cook: medium-light skin tone",
      "emoji": "рџ§‘рџЏјвЂЌрџЌі",
      "codePoints": ["1F9D1", "1F3FC", "200D", "1F373"],
      "order": 937,
      "sequenceType": "zwj",
      "active": true
    },
    {
      "index": 77,
      "row": 4,
      "column": 13,
      "x": 218,
      "y": 106,
      "width": 12,
      "height": 12,
      "key": "cookMediumSkinTone",
      "name": "cook: medium skin tone",
      "emoji": "рџ§‘рџЏЅвЂЌрџЌі",
      "codePoints": ["1F9D1", "1F3FD", "200D", "1F373"],
      "order": 938,
      "sequenceType": "zwj",
      "active": true
    },
    {
      "index": 78,
      "row": 4,
      "column": 14,
      "x": 234,
      "y": 106,
      "width": 12,
      "height": 12,
      "key": "cookMediumDarkSkinTone",
      "name": "cook: medium-dark skin tone",
      "emoji": "рџ§‘рџЏѕвЂЌрџЌі",
      "codePoints": ["1F9D1", "1F3FE", "200D", "1F373"],
      "order": 939,
      "sequenceType": "zwj",
      "active": true
    },
    {
      "index": 79,
      "row": 4,
      "column": 15,
      "x": 250,
      "y": 106,
      "width": 12,
      "height": 12,
      "key": "cookDarkSkinTone",
      "name": "cook: dark skin tone",
      "emoji": "рџ§‘рџЏївЂЌрџЌі",
      "codePoints": ["1F9D1", "1F3FF", "200D", "1F373"],
      "order": 940,
      "sequenceType": "zwj",
      "active": true
    },
    {
      "index": 80,
      "row": 5,
      "column": 0,
      "x": 10,
      "y": 122,
      "width": 12,
      "height": 12,
      "key": "manCookLightSkinTone",
      "name": "man cook: light skin tone",
      "emoji": "рџ‘ЁрџЏ»вЂЌрџЌі",
      "codePoints": ["1F468", "1F3FB", "200D", "1F373"],
      "order": 942,
      "sequenceType": "zwj",
      "active": true
    },
    {
      "index": 81,
      "row": 5,
      "column": 1,
      "x": 26,
      "y": 122,
      "width": 12,
      "height": 12,
      "key": "manCookMediumLightSkinTone",
      "name": "man cook: medium-light skin tone",
      "emoji": "рџ‘ЁрџЏјвЂЌрџЌі",
      "codePoints": ["1F468", "1F3FC", "200D", "1F373"],
      "order": 943,
      "sequenceType": "zwj",
      "active": true
    },
    {
      "index": 82,
      "row": 5,
      "column": 2,
      "x": 42,
      "y": 122,
      "width": 12,
      "height": 12,
      "key": "manCookMediumSkinTone",
      "name": "man cook: medium skin tone",
      "emoji": "рџ‘ЁрџЏЅвЂЌрџЌі",
      "codePoints": ["1F468", "1F3FD", "200D", "1F373"],
      "order": 944,
      "sequenceType": "zwj",
      "active": true
    },
    {
      "index": 83,
      "row": 5,
      "column": 3,
      "x": 58,
      "y": 122,
      "width": 12,
      "height": 12,
      "key": "manCookMediumDarkSkinTone",
      "name": "man cook: medium-dark skin tone",
      "emoji": "рџ‘ЁрџЏѕвЂЌрџЌі",
      "codePoints": ["1F468", "1F3FE", "200D", "1F373"],
      "order": 945,
      "sequenceType": "zwj",
      "active": true
    },
    {
      "index": 84,
      "row": 5,
      "column": 4,
      "x": 74,
      "y": 122,
      "width": 12,
      "height": 12,
      "key": "manCookDarkSkinTone",
      "name": "man cook: dark skin tone",
      "emoji": "рџ‘ЁрџЏївЂЌрџЌі",
      "codePoints": ["1F468", "1F3FF", "200D", "1F373"],
      "order": 946,
      "sequenceType": "zwj",
      "active": true
    },
    {
      "index": 85,
      "row": 5,
      "column": 5,
      "x": 90,
      "y": 122,
      "width": 12,
      "height": 12,
      "key": "womanCookLightSkinTone",
      "name": "woman cook: light skin tone",
      "emoji": "рџ‘©рџЏ»вЂЌрџЌі",
      "codePoints": ["1F469", "1F3FB", "200D", "1F373"],
      "order": 948,
      "sequenceType": "zwj",
      "active": true
    },
    {
      "index": 86,
      "row": 5,
      "column": 6,
      "x": 106,
      "y": 122,
      "width": 12,
      "height": 12,
      "key": "womanCookMediumLightSkinTone",
      "name": "woman cook: medium-light skin tone",
      "emoji": "рџ‘©рџЏјвЂЌрџЌі",
      "codePoints": ["1F469", "1F3FC", "200D", "1F373"],
      "order": 949,
      "sequenceType": "zwj",
      "active": true
    },
    {
      "index": 87,
      "row": 5,
      "column": 7,
      "x": 122,
      "y": 122,
      "width": 12,
      "height": 12,
      "key": "womanCookMediumSkinTone",
      "name": "woman cook: medium skin tone",
      "emoji": "рџ‘©рџЏЅвЂЌрџЌі",
      "codePoints": ["1F469", "1F3FD", "200D", "1F373"],
      "order": 950,
      "sequenceType": "zwj",
      "active": true
    },
    {
      "index": 88,
      "row": 5,
      "column": 8,
      "x": 138,
      "y": 122,
      "width": 12,
      "height": 12,
      "key": "womanCookMediumDarkSkinTone",
      "name": "woman cook: medium-dark skin tone",
      "emoji": "рџ‘©рџЏѕвЂЌрџЌі",
      "codePoints": ["1F469", "1F3FE", "200D", "1F373"],
      "order": 951,
      "sequenceType": "zwj",
      "active": true
    },
    {
      "index": 89,
      "row": 5,
      "column": 9,
      "x": 154,
      "y": 122,
      "width": 12,
      "height": 12,
      "key": "womanCookDarkSkinTone",
      "name": "woman cook: dark skin tone",
      "emoji": "рџ‘©рџЏївЂЌрџЌі",
      "codePoints": ["1F469", "1F3FF", "200D", "1F373"],
      "order": 952,
      "sequenceType": "zwj",
      "active": true
    },
    {
      "index": 90,
      "row": 5,
      "column": 10,
      "x": 170,
      "y": 122,
      "width": 12,
      "height": 12,
      "key": "mechanicLightSkinTone",
      "name": "mechanic: light skin tone",
      "emoji": "рџ§‘рџЏ»вЂЌрџ”§",
      "codePoints": ["1F9D1", "1F3FB", "200D", "1F527"],
      "order": 954,
      "sequenceType": "zwj",
      "active": true
    },
    {
      "index": 91,
      "row": 5,
      "column": 11,
      "x": 186,
      "y": 122,
      "width": 12,
      "height": 12,
      "key": "mechanicMediumLightSkinTone",
      "name": "mechanic: medium-light skin tone",
      "emoji": "рџ§‘рџЏјвЂЌрџ”§",
      "codePoints": ["1F9D1", "1F3FC", "200D", "1F527"],
      "order": 955,
      "sequenceType": "zwj",
      "active": true
    },
    {
      "index": 92,
      "row": 5,
      "column": 12,
      "x": 202,
      "y": 122,
      "width": 12,
      "height": 12,
      "key": "mechanicMediumSkinTone",
      "name": "mechanic: medium skin tone",
      "emoji": "рџ§‘рџЏЅвЂЌрџ”§",
      "codePoints": ["1F9D1", "1F3FD", "200D", "1F527"],
      "order": 956,
      "sequenceType": "zwj",
      "active": true
    },
    {
      "index": 93,
      "row": 5,
      "column": 13,
      "x": 218,
      "y": 122,
      "width": 12,
      "height": 12,
      "key": "mechanicMediumDarkSkinTone",
      "name": "mechanic: medium-dark skin tone",
      "emoji": "рџ§‘рџЏѕвЂЌрџ”§",
      "codePoints": ["1F9D1", "1F3FE", "200D", "1F527"],
      "order": 957,
      "sequenceType": "zwj",
      "active": true
    },
    {
      "index": 94,
      "row": 5,
      "column": 14,
      "x": 234,
      "y": 122,
      "width": 12,
      "height": 12,
      "key": "mechanicDarkSkinTone",
      "name": "mechanic: dark skin tone",
      "emoji": "рџ§‘рџЏївЂЌрџ”§",
      "codePoints": ["1F9D1", "1F3FF", "200D", "1F527"],
      "order": 958,
      "sequenceType": "zwj",
      "active": true
    },
    {
      "index": 95,
      "row": 5,
      "column": 15,
      "x": 250,
      "y": 122,
      "width": 12,
      "height": 12,
      "key": "manMechanicLightSkinTone",
      "name": "man mechanic: light skin tone",
      "emoji": "рџ‘ЁрџЏ»вЂЌрџ”§",
      "codePoints": ["1F468", "1F3FB", "200D", "1F527"],
      "order": 960,
      "sequenceType": "zwj",
      "active": true
    },
    {
      "index": 96,
      "row": 6,
      "column": 0,
      "x": 10,
      "y": 138,
      "width": 12,
      "height": 12,
      "key": "manMechanicMediumLightSkinTone",
      "name": "man mechanic: medium-light skin tone",
      "emoji": "рџ‘ЁрџЏјвЂЌрџ”§",
      "codePoints": ["1F468", "1F3FC", "200D", "1F527"],
      "order": 961,
      "sequenceType": "zwj",
      "active": true
    },
    {
      "index": 97,
      "row": 6,
      "column": 1,
      "x": 26,
      "y": 138,
      "width": 12,
      "height": 12,
      "key": "manMechanicMediumSkinTone",
      "name": "man mechanic: medium skin tone",
      "emoji": "рџ‘ЁрџЏЅвЂЌрџ”§",
      "codePoints": ["1F468", "1F3FD", "200D", "1F527"],
      "order": 962,
      "sequenceType": "zwj",
      "active": true
    },
    {
      "index": 98,
      "row": 6,
      "column": 2,
      "x": 42,
      "y": 138,
      "width": 12,
      "height": 12,
      "key": "manMechanicMediumDarkSkinTone",
      "name": "man mechanic: medium-dark skin tone",
      "emoji": "рџ‘ЁрџЏѕвЂЌрџ”§",
      "codePoints": ["1F468", "1F3FE", "200D", "1F527"],
      "order": 963,
      "sequenceType": "zwj",
      "active": true
    },
    {
      "index": 99,
      "row": 6,
      "column": 3,
      "x": 58,
      "y": 138,
      "width": 12,
      "height": 12,
      "key": "manMechanicDarkSkinTone",
      "name": "man mechanic: dark skin tone",
      "emoji": "рџ‘ЁрџЏївЂЌрџ”§",
      "codePoints": ["1F468", "1F3FF", "200D", "1F527"],
      "order": 964,
      "sequenceType": "zwj",
      "active": true
    },
    {
      "index": 100,
      "row": 6,
      "column": 4,
      "x": 74,
      "y": 138,
      "width": 12,
      "height": 12,
      "key": "womanMechanicLightSkinTone",
      "name": "woman mechanic: light skin tone",
      "emoji": "рџ‘©рџЏ»вЂЌрџ”§",
      "codePoints": ["1F469", "1F3FB", "200D", "1F527"],
      "order": 966,
      "sequenceType": "zwj",
      "active": true
    },
    {
      "index": 101,
      "row": 6,
      "column": 5,
      "x": 90,
      "y": 138,
      "width": 12,
      "height": 12,
      "key": "womanMechanicMediumLightSkinTone",
      "name": "woman mechanic: medium-light skin tone",
      "emoji": "рџ‘©рџЏјвЂЌрџ”§",
      "codePoints": ["1F469", "1F3FC", "200D", "1F527"],
      "order": 967,
      "sequenceType": "zwj",
      "active": true
    },
    {
      "index": 102,
      "row": 6,
      "column": 6,
      "x": 106,
      "y": 138,
      "width": 12,
      "height": 12,
      "key": "womanMechanicMediumSkinTone",
      "name": "woman mechanic: medium skin tone",
      "emoji": "рџ‘©рџЏЅвЂЌрџ”§",
      "codePoints": ["1F469", "1F3FD", "200D", "1F527"],
      "order": 968,
      "sequenceType": "zwj",
      "active": true
    },
    {
      "index": 103,
      "row": 6,
      "column": 7,
      "x": 122,
      "y": 138,
      "width": 12,
      "height": 12,
      "key": "womanMechanicMediumDarkSkinTone",
      "name": "woman mechanic: medium-dark skin tone",
      "emoji": "рџ‘©рџЏѕвЂЌрџ”§",
      "codePoints": ["1F469", "1F3FE", "200D", "1F527"],
      "order": 969,
      "sequenceType": "zwj",
      "active": true
    },
    {
      "index": 104,
      "row": 6,
      "column": 8,
      "x": 138,
      "y": 138,
      "width": 12,
      "height": 12,
      "key": "womanMechanicDarkSkinTone",
      "name": "woman mechanic: dark skin tone",
      "emoji": "рџ‘©рџЏївЂЌрџ”§",
      "codePoints": ["1F469", "1F3FF", "200D", "1F527"],
      "order": 970,
      "sequenceType": "zwj",
      "active": true
    },
    {
      "index": 105,
      "row": 6,
      "column": 9,
      "x": 154,
      "y": 138,
      "width": 12,
      "height": 12,
      "key": "factoryWorkerLightSkinTone",
      "name": "factory worker: light skin tone",
      "emoji": "рџ§‘рџЏ»вЂЌрџЏ­",
      "codePoints": ["1F9D1", "1F3FB", "200D", "1F3ED"],
      "order": 972,
      "sequenceType": "zwj",
      "active": true
    },
    {
      "index": 106,
      "row": 6,
      "column": 10,
      "x": 170,
      "y": 138,
      "width": 12,
      "height": 12,
      "key": "factoryWorkerMediumLightSkinTone",
      "name": "factory worker: medium-light skin tone",
      "emoji": "рџ§‘рџЏјвЂЌрџЏ­",
      "codePoints": ["1F9D1", "1F3FC", "200D", "1F3ED"],
      "order": 973,
      "sequenceType": "zwj",
      "active": true
    },
    {
      "index": 107,
      "row": 6,
      "column": 11,
      "x": 186,
      "y": 138,
      "width": 12,
      "height": 12,
      "key": "factoryWorkerMediumSkinTone",
      "name": "factory worker: medium skin tone",
      "emoji": "рџ§‘рџЏЅвЂЌрџЏ­",
      "codePoints": ["1F9D1", "1F3FD", "200D", "1F3ED"],
      "order": 974,
      "sequenceType": "zwj",
      "active": true
    },
    {
      "index": 108,
      "row": 6,
      "column": 12,
      "x": 202,
      "y": 138,
      "width": 12,
      "height": 12,
      "key": "factoryWorkerMediumDarkSkinTone",
      "name": "factory worker: medium-dark skin tone",
      "emoji": "рџ§‘рџЏѕвЂЌрџЏ­",
      "codePoints": ["1F9D1", "1F3FE", "200D", "1F3ED"],
      "order": 975,
      "sequenceType": "zwj",
      "active": true
    },
    {
      "index": 109,
      "row": 6,
      "column": 13,
      "x": 218,
      "y": 138,
      "width": 12,
      "height": 12,
      "key": "factoryWorkerDarkSkinTone",
      "name": "factory worker: dark skin tone",
      "emoji": "рџ§‘рџЏївЂЌрџЏ­",
      "codePoints": ["1F9D1", "1F3FF", "200D", "1F3ED"],
      "order": 976,
      "sequenceType": "zwj",
      "active": true
    },
    {
      "index": 110,
      "row": 6,
      "column": 14,
      "x": 234,
      "y": 138,
      "width": 12,
      "height": 12,
      "key": "manFactoryWorkerLightSkinTone",
      "name": "man factory worker: light skin tone",
      "emoji": "рџ‘ЁрџЏ»вЂЌрџЏ­",
      "codePoints": ["1F468", "1F3FB", "200D", "1F3ED"],
      "order": 978,
      "sequenceType": "zwj",
      "active": true
    },
    {
      "index": 111,
      "row": 6,
      "column": 15,
      "x": 250,
      "y": 138,
      "width": 12,
      "height": 12,
      "key": "manFactoryWorkerMediumLightSkinTone",
      "name": "man factory worker: medium-light skin tone",
      "emoji": "рџ‘ЁрџЏјвЂЌрџЏ­",
      "codePoints": ["1F468", "1F3FC", "200D", "1F3ED"],
      "order": 979,
      "sequenceType": "zwj",
      "active": true
    },
    {
      "index": 112,
      "row": 7,
      "column": 0,
      "x": 10,
      "y": 154,
      "width": 12,
      "height": 12,
      "key": "manFactoryWorkerMediumSkinTone",
      "name": "man factory worker: medium skin tone",
      "emoji": "рџ‘ЁрџЏЅвЂЌрџЏ­",
      "codePoints": ["1F468", "1F3FD", "200D", "1F3ED"],
      "order": 980,
      "sequenceType": "zwj",
      "active": true
    },
    {
      "index": 113,
      "row": 7,
      "column": 1,
      "x": 26,
      "y": 154,
      "width": 12,
      "height": 12,
      "key": "manFactoryWorkerMediumDarkSkinTone",
      "name": "man factory worker: medium-dark skin tone",
      "emoji": "рџ‘ЁрџЏѕвЂЌрџЏ­",
      "codePoints": ["1F468", "1F3FE", "200D", "1F3ED"],
      "order": 981,
      "sequenceType": "zwj",
      "active": true
    },
    {
      "index": 114,
      "row": 7,
      "column": 2,
      "x": 42,
      "y": 154,
      "width": 12,
      "height": 12,
      "key": "manFactoryWorkerDarkSkinTone",
      "name": "man factory worker: dark skin tone",
      "emoji": "рџ‘ЁрџЏївЂЌрџЏ­",
      "codePoints": ["1F468", "1F3FF", "200D", "1F3ED"],
      "order": 982,
      "sequenceType": "zwj",
      "active": true
    },
    {
      "index": 115,
      "row": 7,
      "column": 3,
      "x": 58,
      "y": 154,
      "width": 12,
      "height": 12,
      "key": "womanFactoryWorkerLightSkinTone",
      "name": "woman factory worker: light skin tone",
      "emoji": "рџ‘©рџЏ»вЂЌрџЏ­",
      "codePoints": ["1F469", "1F3FB", "200D", "1F3ED"],
      "order": 984,
      "sequenceType": "zwj",
      "active": true
    },
    {
      "index": 116,
      "row": 7,
      "column": 4,
      "x": 74,
      "y": 154,
      "width": 12,
      "height": 12,
      "key": "womanFactoryWorkerMediumLightSkinTone",
      "name": "woman factory worker: medium-light skin tone",
      "emoji": "рџ‘©рџЏјвЂЌрџЏ­",
      "codePoints": ["1F469", "1F3FC", "200D", "1F3ED"],
      "order": 985,
      "sequenceType": "zwj",
      "active": true
    },
    {
      "index": 117,
      "row": 7,
      "column": 5,
      "x": 90,
      "y": 154,
      "width": 12,
      "height": 12,
      "key": "womanFactoryWorkerMediumSkinTone",
      "name": "woman factory worker: medium skin tone",
      "emoji": "рџ‘©рџЏЅвЂЌрџЏ­",
      "codePoints": ["1F469", "1F3FD", "200D", "1F3ED"],
      "order": 986,
      "sequenceType": "zwj",
      "active": true
    },
    {
      "index": 118,
      "row": 7,
      "column": 6,
      "x": 106,
      "y": 154,
      "width": 12,
      "height": 12,
      "key": "womanFactoryWorkerMediumDarkSkinTone",
      "name": "woman factory worker: medium-dark skin tone",
      "emoji": "рџ‘©рџЏѕвЂЌрџЏ­",
      "codePoints": ["1F469", "1F3FE", "200D", "1F3ED"],
      "order": 987,
      "sequenceType": "zwj",
      "active": true
    },
    {
      "index": 119,
      "row": 7,
      "column": 7,
      "x": 122,
      "y": 154,
      "width": 12,
      "height": 12,
      "key": "womanFactoryWorkerDarkSkinTone",
      "name": "woman factory worker: dark skin tone",
      "emoji": "рџ‘©рџЏївЂЌрџЏ­",
      "codePoints": ["1F469", "1F3FF", "200D", "1F3ED"],
      "order": 988,
      "sequenceType": "zwj",
      "active": true
    },
    {
      "index": 120,
      "row": 7,
      "column": 8,
      "x": 138,
      "y": 154,
      "width": 12,
      "height": 12,
      "key": "officeWorkerLightSkinTone",
      "name": "office worker: light skin tone",
      "emoji": "рџ§‘рџЏ»вЂЌрџ’ј",
      "codePoints": ["1F9D1", "1F3FB", "200D", "1F4BC"],
      "order": 990,
      "sequenceType": "zwj",
      "active": true
    },
    {
      "index": 121,
      "row": 7,
      "column": 9,
      "x": 154,
      "y": 154,
      "width": 12,
      "height": 12,
      "key": "officeWorkerMediumLightSkinTone",
      "name": "office worker: medium-light skin tone",
      "emoji": "рџ§‘рџЏјвЂЌрџ’ј",
      "codePoints": ["1F9D1", "1F3FC", "200D", "1F4BC"],
      "order": 991,
      "sequenceType": "zwj",
      "active": true
    },
    {
      "index": 122,
      "row": 7,
      "column": 10,
      "x": 170,
      "y": 154,
      "width": 12,
      "height": 12,
      "key": "officeWorkerMediumSkinTone",
      "name": "office worker: medium skin tone",
      "emoji": "рџ§‘рџЏЅвЂЌрџ’ј",
      "codePoints": ["1F9D1", "1F3FD", "200D", "1F4BC"],
      "order": 992,
      "sequenceType": "zwj",
      "active": true
    },
    {
      "index": 123,
      "row": 7,
      "column": 11,
      "x": 186,
      "y": 154,
      "width": 12,
      "height": 12,
      "key": "officeWorkerMediumDarkSkinTone",
      "name": "office worker: medium-dark skin tone",
      "emoji": "рџ§‘рџЏѕвЂЌрџ’ј",
      "codePoints": ["1F9D1", "1F3FE", "200D", "1F4BC"],
      "order": 993,
      "sequenceType": "zwj",
      "active": true
    },
    {
      "index": 124,
      "row": 7,
      "column": 12,
      "x": 202,
      "y": 154,
      "width": 12,
      "height": 12,
      "key": "officeWorkerDarkSkinTone",
      "name": "office worker: dark skin tone",
      "emoji": "рџ§‘рџЏївЂЌрџ’ј",
      "codePoints": ["1F9D1", "1F3FF", "200D", "1F4BC"],
      "order": 994,
      "sequenceType": "zwj",
      "active": true
    },
    {
      "index": 125,
      "row": 7,
      "column": 13,
      "x": 218,
      "y": 154,
      "width": 12,
      "height": 12,
      "key": "manOfficeWorkerLightSkinTone",
      "name": "man office worker: light skin tone",
      "emoji": "рџ‘ЁрџЏ»вЂЌрџ’ј",
      "codePoints": ["1F468", "1F3FB", "200D", "1F4BC"],
      "order": 996,
      "sequenceType": "zwj",
      "active": true
    },
    {
      "index": 126,
      "row": 7,
      "column": 14,
      "x": 234,
      "y": 154,
      "width": 12,
      "height": 12,
      "key": "manOfficeWorkerMediumLightSkinTone",
      "name": "man office worker: medium-light skin tone",
      "emoji": "рџ‘ЁрџЏјвЂЌрџ’ј",
      "codePoints": ["1F468", "1F3FC", "200D", "1F4BC"],
      "order": 997,
      "sequenceType": "zwj",
      "active": true
    },
    {
      "index": 127,
      "row": 7,
      "column": 15,
      "x": 250,
      "y": 154,
      "width": 12,
      "height": 12,
      "key": "manOfficeWorkerMediumSkinTone",
      "name": "man office worker: medium skin tone",
      "emoji": "рџ‘ЁрџЏЅвЂЌрџ’ј",
      "codePoints": ["1F468", "1F3FD", "200D", "1F4BC"],
      "order": 998,
      "sequenceType": "zwj",
      "active": true
    }
  ]
}
